{"traceEvents":[{"name":"lexer_load_file_text","cat":"function","ph":"X","ts":10,"pid":9036,"tid":0,"dur":65},{"name":"generate_text_token","cat":"function","ph":"X","ts":95,"pid":9036,"tid":0,"dur":1},{"name":"generate_text_token","cat":"function","ph":"X","ts":104,"pid":9036,"tid":0,"dur":1},{"name":"gen TokenTypeOperatorEqual","cat":"function","ph":"X","ts":106,"pid":9036,"tid":0,"dur":1},{"name":"generate_number_literal_token","cat":"function","ph":"X","ts":107,"pid":9036,"tid":0,"dur":1},{"name":"gen TokenTypeAssignmentMinus","cat":"function","ph":"X","ts":108,"pid":9036,"tid":0,"dur":1},{"name":"gen token separator","cat":"function","ph":"X","ts":109,"pid":9036,"tid":0,"dur":1},{"name":"generate_number_literal_token","cat":"function","ph":"X","ts":110,"pid":9036,"tid":0,"dur":1},{"name":"gen TokenTypeAssignmentMinus","cat":"function","ph":"X","ts":111,"pid":9036,"tid":0,"dur":1},{"name":"generate_number_literal_token","cat":"function","ph":"X","ts":111,"pid":9036,"tid":0,"dur":1},{"name":"gen TokenTypeAssignmentMinus","cat":"function","ph":"X","ts":113,"pid":9036,"tid":0,"dur":1},{"name":"generate_number_literal_token","cat":"function","ph":"X","ts":113,"pid":9036,"tid":0,"dur":1},{"name":"gen TokenTypeAssignmentMinus","cat":"function","ph":"X","ts":114,"pid":9036,"tid":0,"dur":1},{"name":"generate_number_literal_token","cat":"function","ph":"X","ts":114,"pid":9036,"tid":0,"dur":1},{"name":"gen TokenTypeAssignmentMinus","cat":"function","ph":"X","ts":115,"pid":9036,"tid":0,"dur":1},{"name":"generate_number_literal_token","cat":"function","ph":"X","ts":115,"pid":9036,"tid":0,"dur":1},{"name":"gen token separator","cat":"function","ph":"X","ts":116,"pid":9036,"tid":0,"dur":1},{"name":"gen TokenTypeAssignmentMinus","cat":"function","ph":"X","ts":117,"pid":9036,"tid":0,"dur":1},{"name":"generate_number_literal_token","cat":"function","ph":"X","ts":117,"pid":9036,"tid":0,"dur":1},{"name":"gen TokenTypeAssignmentMinus","cat":"function","ph":"X","ts":118,"pid":9036,"tid":0,"dur":1},{"name":"generate_number_literal_token","cat":"function","ph":"X","ts":119,"pid":9036,"tid":0,"dur":1},{"name":"gen token newline","cat":"function","ph":"X","ts":119,"pid":9036,"tid":0,"dur":1},{"name":"generate_text_token","cat":"function","ph":"X","ts":120,"pid":9036,"tid":0,"dur":1},{"name":"generate_text_token","cat":"function","ph":"X","ts":121,"pid":9036,"tid":0,"dur":1},{"name":"gen TokenTypeOperatorEqual","cat":"function","ph":"X","ts":122,"pid":9036,"tid":0,"dur":1},{"name":"generate_number_literal_token","cat":"function","ph":"X","ts":122,"pid":9036,"tid":0,"dur":1},{"name":"gen TokenTypeAssignmentPlus","cat":"function","ph":"X","ts":123,"pid":9036,"tid":0,"dur":1},{"name":"generate_number_literal_token","cat":"function","ph":"X","ts":123,"pid":9036,"tid":0,"dur":1},{"name":"gen TokenTypeAssignmentModulus","cat":"function","ph":"X","ts":124,"pid":9036,"tid":0,"dur":1},{"name":"generate_number_literal_token","cat":"function","ph":"X","ts":125,"pid":9036,"tid":0,"dur":1},{"name":"gen TokenTypeAssignmentDivide","cat":"function","ph":"X","ts":125,"pid":9036,"tid":0,"dur":1},{"name":"generate_number_literal_token","cat":"function","ph":"X","ts":126,"pid":9036,"tid":0,"dur":1},{"name":"gen token newline","cat":"function","ph":"X","ts":127,"pid":9036,"tid":0,"dur":1},{"name":"generate_text_token","cat":"function","ph":"X","ts":127,"pid":9036,"tid":0,"dur":1},{"name":"generate_text_token","cat":"function","ph":"X","ts":128,"pid":9036,"tid":0,"dur":1},{"name":"gen TokenTypeOperatorEqual","cat":"function","ph":"X","ts":129,"pid":9036,"tid":0,"dur":1},{"name":"generate_number_literal_token","cat":"function","ph":"X","ts":130,"pid":9036,"tid":0,"dur":1},{"name":"gen TokenTypeAssignmentMinus","cat":"function","ph":"X","ts":131,"pid":9036,"tid":0,"dur":1},{"name":"generate_number_literal_token","cat":"function","ph":"X","ts":131,"pid":9036,"tid":0,"dur":1},{"name":"gen TokenTypeAssignmentMinus","cat":"function","ph":"X","ts":132,"pid":9036,"tid":0,"dur":1},{"name":"generate_number_literal_token","cat":"function","ph":"X","ts":132,"pid":9036,"tid":0,"dur":1},{"name":"gen TokenTypeAssignmentMinus","cat":"function","ph":"X","ts":133,"pid":9036,"tid":0,"dur":1},{"name":"gen TokenTypeAssignmentMinus","cat":"function","ph":"X","ts":134,"pid":9036,"tid":0,"dur":1},{"name":"generate_number_literal_token","cat":"function","ph":"X","ts":134,"pid":9036,"tid":0,"dur":1},{"name":"gen TokenTypeAssignmentMultiply","cat":"function","ph":"X","ts":135,"pid":9036,"tid":0,"dur":1},{"name":"generate_number_literal_token","cat":"function","ph":"X","ts":135,"pid":9036,"tid":0,"dur":1},{"name":"gen TokenTypeAssignmentPlus","cat":"function","ph":"X","ts":136,"pid":9036,"tid":0,"dur":1},{"name":"generate_number_literal_token","cat":"function","ph":"X","ts":137,"pid":9036,"tid":0,"dur":1},{"name":"gen token newline","cat":"function","ph":"X","ts":137,"pid":9036,"tid":0,"dur":1},{"name":"generate_text_token","cat":"function","ph":"X","ts":138,"pid":9036,"tid":0,"dur":1},{"name":"generate_text_token","cat":"function","ph":"X","ts":139,"pid":9036,"tid":0,"dur":1},{"name":"gen TokenTypeOperatorEqual","cat":"function","ph":"X","ts":139,"pid":9036,"tid":0,"dur":1},{"name":"generate_text_token","cat":"function","ph":"X","ts":140,"pid":9036,"tid":0,"dur":1},{"name":"gen TokenTypeAssignmentPlus","cat":"function","ph":"X","ts":141,"pid":9036,"tid":0,"dur":1},{"name":"generate_text_token","cat":"function","ph":"X","ts":141,"pid":9036,"tid":0,"dur":1},{"name":"gen TokenTypeAssignmentPlus","cat":"function","ph":"X","ts":142,"pid":9036,"tid":0,"dur":1},{"name":"generate_text_token","cat":"function","ph":"X","ts":143,"pid":9036,"tid":0,"dur":1},{"name":"gen token newline","cat":"function","ph":"X","ts":144,"pid":9036,"tid":0,"dur":1},{"name":"generate_text_token","cat":"function","ph":"X","ts":144,"pid":9036,"tid":0,"dur":1},{"name":"generate_text_token","cat":"function","ph":"X","ts":145,"pid":9036,"tid":0,"dur":1},{"name":"gen TokenTypeOperatorEqual","cat":"function","ph":"X","ts":145,"pid":9036,"tid":0,"dur":1},{"name":"gen token separator","cat":"function","ph":"X","ts":146,"pid":9036,"tid":0,"dur":1},{"name":"generate_number_literal_token","cat":"function","ph":"X","ts":148,"pid":9036,"tid":0,"dur":1},{"name":"gen TokenTypeAssignmentPlus","cat":"function","ph":"X","ts":149,"pid":9036,"tid":0,"dur":1},{"name":"generate_number_literal_token","cat":"function","ph":"X","ts":150,"pid":9036,"tid":0,"dur":1},{"name":"gen TokenTypeAssignmentMultiply","cat":"function","ph":"X","ts":150,"pid":9036,"tid":0,"dur":1},{"name":"gen token separator","cat":"function","ph":"X","ts":151,"pid":9036,"tid":0,"dur":1},{"name":"generate_number_literal_token","cat":"function","ph":"X","ts":152,"pid":9036,"tid":0,"dur":1},{"name":"gen TokenTypeAssignmentDivide","cat":"function","ph":"X","ts":152,"pid":9036,"tid":0,"dur":1},{"name":"gen token separator","cat":"function","ph":"X","ts":153,"pid":9036,"tid":0,"dur":1},{"name":"gen TokenTypeAssignmentMultiply","cat":"function","ph":"X","ts":153,"pid":9036,"tid":0,"dur":1},{"name":"generate_number_literal_token","cat":"function","ph":"X","ts":154,"pid":9036,"tid":0,"dur":1},{"name":"gen token separator","cat":"function","ph":"X","ts":155,"pid":9036,"tid":0,"dur":1},{"name":"gen token separator","cat":"function","ph":"X","ts":155,"pid":9036,"tid":0,"dur":1},{"name":"gen TokenTypeAssignmentPlus","cat":"function","ph":"X","ts":156,"pid":9036,"tid":0,"dur":1},{"name":"generate_number_literal_token","cat":"function","ph":"X","ts":156,"pid":9036,"tid":0,"dur":1},{"name":"gen TokenTypeAssignmentMinus","cat":"function","ph":"X","ts":157,"pid":9036,"tid":0,"dur":1},{"name":"generate_number_literal_token","cat":"function","ph":"X","ts":158,"pid":9036,"tid":0,"dur":1},{"name":"gen TokenTypeAssignmentMinus","cat":"function","ph":"X","ts":158,"pid":9036,"tid":0,"dur":1},{"name":"generate_number_literal_token","cat":"function","ph":"X","ts":159,"pid":9036,"tid":0,"dur":1},{"name":"gen token separator","cat":"function","ph":"X","ts":159,"pid":9036,"tid":0,"dur":1},{"name":"gen TokenTypeAssignmentMultiply","cat":"function","ph":"X","ts":160,"pid":9036,"tid":0,"dur":1},{"name":"generate_number_literal_token","cat":"function","ph":"X","ts":160,"pid":9036,"tid":0,"dur":1},{"name":"gen TokenTypeAssignmentPlus","cat":"function","ph":"X","ts":161,"pid":9036,"tid":0,"dur":1},{"name":"gen token separator","cat":"function","ph":"X","ts":162,"pid":9036,"tid":0,"dur":1},{"name":"generate_number_literal_token","cat":"function","ph":"X","ts":162,"pid":9036,"tid":0,"dur":1},{"name":"gen TokenTypeAssignmentPlus","cat":"function","ph":"X","ts":163,"pid":9036,"tid":0,"dur":1},{"name":"gen token separator","cat":"function","ph":"X","ts":164,"pid":9036,"tid":0,"dur":1},{"name":"gen TokenTypeAssignmentPlus","cat":"function","ph":"X","ts":164,"pid":9036,"tid":0,"dur":1},{"name":"gen token separator","cat":"function","ph":"X","ts":165,"pid":9036,"tid":0,"dur":1},{"name":"gen TokenTypeAssignmentMinus","cat":"function","ph":"X","ts":165,"pid":9036,"tid":0,"dur":1},{"name":"generate_number_literal_token","cat":"function","ph":"X","ts":166,"pid":9036,"tid":0,"dur":1},{"name":"gen TokenTypeAssignmentMinus","cat":"function","ph":"X","ts":167,"pid":9036,"tid":0,"dur":1},{"name":"generate_number_literal_token","cat":"function","ph":"X","ts":167,"pid":9036,"tid":0,"dur":1},{"name":"gen token separator","cat":"function","ph":"X","ts":168,"pid":9036,"tid":0,"dur":1},{"name":"gen token newline","cat":"function","ph":"X","ts":168,"pid":9036,"tid":0,"dur":1},{"name":"generate_text_token","cat":"function","ph":"X","ts":169,"pid":9036,"tid":0,"dur":1},{"name":"gen TokenTypeOperatorEqual","cat":"function","ph":"X","ts":170,"pid":9036,"tid":0,"dur":1},{"name":"generate_number_literal_token","cat":"function","ph":"X","ts":170,"pid":9036,"tid":0,"dur":1},{"name":"gen token newline","cat":"function","ph":"X","ts":171,"pid":9036,"tid":0,"dur":1},{"name":"generate_text_token","cat":"function","ph":"X","ts":172,"pid":9036,"tid":0,"dur":1},{"name":"gen '='","cat":"function","ph":"X","ts":172,"pid":9036,"tid":0,"dur":1},{"name":"generate_text_token","cat":"function","ph":"X","ts":173,"pid":9036,"tid":0,"dur":1},{"name":"gen token newline","cat":"function","ph":"X","ts":174,"pid":9036,"tid":0,"dur":1},{"name":"generate_text_token","cat":"function","ph":"X","ts":176,"pid":9036,"tid":0,"dur":1},{"name":"gen '='","cat":"function","ph":"X","ts":176,"pid":9036,"tid":0,"dur":1},{"name":"generate_text_token","cat":"function","ph":"X","ts":177,"pid":9036,"tid":0,"dur":1},{"name":"gen token newline","cat":"function","ph":"X","ts":178,"pid":9036,"tid":0,"dur":1},{"name":"generate_text_token","cat":"function","ph":"X","ts":178,"pid":9036,"tid":0,"dur":1},{"name":"gen '='","cat":"function","ph":"X","ts":179,"pid":9036,"tid":0,"dur":1},{"name":"generate_text_token","cat":"function","ph":"X","ts":180,"pid":9036,"tid":0,"dur":1},{"name":"gen token newline","cat":"function","ph":"X","ts":181,"pid":9036,"tid":0,"dur":1},{"name":"generate_text_token","cat":"function","ph":"X","ts":181,"pid":9036,"tid":0,"dur":1},{"name":"gen '='","cat":"function","ph":"X","ts":182,"pid":9036,"tid":0,"dur":1},{"name":"generate_text_token","cat":"function","ph":"X","ts":183,"pid":9036,"tid":0,"dur":1},{"name":"gen token newline","cat":"function","ph":"X","ts":183,"pid":9036,"tid":0,"dur":1},{"name":"generate_text_token","cat":"function","ph":"X","ts":184,"pid":9036,"tid":0,"dur":1},{"name":"gen TokenTypeOperatorEqual","cat":"function","ph":"X","ts":185,"pid":9036,"tid":0,"dur":1},{"name":"generate_text_token","cat":"function","ph":"X","ts":185,"pid":9036,"tid":0,"dur":1},{"name":"gen token newline","cat":"function","ph":"X","ts":186,"pid":9036,"tid":0,"dur":1},{"name":"generate_text_token","cat":"function","ph":"X","ts":187,"pid":9036,"tid":0,"dur":1},{"name":"generate_text_token","cat":"function","ph":"X","ts":191,"pid":9036,"tid":0,"dur":1},{"name":"gen token newline","cat":"function","ph":"X","ts":192,"pid":9036,"tid":0,"dur":1},{"name":"generate_text_token","cat":"function","ph":"X","ts":193,"pid":9036,"tid":0,"dur":1},{"name":"generate_text_token","cat":"function","ph":"X","ts":193,"pid":9036,"tid":0,"dur":1},{"name":"generate_text_token","cat":"function","ph":"X","ts":201,"pid":9036,"tid":0,"dur":1},{"name":"gen token newline","cat":"function","ph":"X","ts":202,"pid":9036,"tid":0,"dur":1},{"name":"generate_text_token","cat":"function","ph":"X","ts":203,"pid":9036,"tid":0,"dur":1},{"name":"generate_text_token","cat":"function","ph":"X","ts":203,"pid":9036,"tid":0,"dur":1},{"name":"generate_text_token","cat":"function","ph":"X","ts":204,"pid":9036,"tid":0,"dur":1},{"name":"generate_text_token","cat":"function","ph":"X","ts":205,"pid":9036,"tid":0,"dur":1},{"name":"gen token newline","cat":"function","ph":"X","ts":206,"pid":9036,"tid":0,"dur":1},{"name":"generate_text_token","cat":"function","ph":"X","ts":206,"pid":9036,"tid":0,"dur":1},{"name":"generate_text_token","cat":"function","ph":"X","ts":207,"pid":9036,"tid":0,"dur":1},{"name":"generate_text_token","cat":"function","ph":"X","ts":208,"pid":9036,"tid":0,"dur":1},{"name":"generate_text_token","cat":"function","ph":"X","ts":209,"pid":9036,"tid":0,"dur":1},{"name":"generate_text_token","cat":"function","ph":"X","ts":209,"pid":9036,"tid":0,"dur":1},{"name":"gen token newline","cat":"function","ph":"X","ts":210,"pid":9036,"tid":0,"dur":1},{"name":"gen token newline","cat":"function","ph":"X","ts":211,"pid":9036,"tid":0,"dur":1},{"name":"generate_text_token","cat":"function","ph":"X","ts":211,"pid":9036,"tid":0,"dur":1},{"name":"generate_text_token","cat":"function","ph":"X","ts":212,"pid":9036,"tid":0,"dur":1},{"name":"gen token separator","cat":"function","ph":"X","ts":213,"pid":9036,"tid":0,"dur":1},{"name":"generate_text_token","cat":"function","ph":"X","ts":214,"pid":9036,"tid":0,"dur":1},{"name":"gen token separator","cat":"function","ph":"X","ts":214,"pid":9036,"tid":0,"dur":1},{"name":"gen token newline","cat":"function","ph":"X","ts":215,"pid":9036,"tid":0,"dur":1},{"name":"generate_text_token","cat":"function","ph":"X","ts":216,"pid":9036,"tid":0,"dur":1},{"name":"generate_text_token","cat":"function","ph":"X","ts":216,"pid":9036,"tid":0,"dur":1},{"name":"gen TokenTypeOperatorEqual","cat":"function","ph":"X","ts":217,"pid":9036,"tid":0,"dur":1},{"name":"generate_text_token","cat":"function","ph":"X","ts":219,"pid":9036,"tid":0,"dur":1},{"name":"gen TokenTypeAssignmentMultiply","cat":"function","ph":"X","ts":220,"pid":9036,"tid":0,"dur":1},{"name":"generate_text_token","cat":"function","ph":"X","ts":221,"pid":9036,"tid":0,"dur":1},{"name":"gen token newline","cat":"function","ph":"X","ts":221,"pid":9036,"tid":0,"dur":1},{"name":"generate_text_token","cat":"function","ph":"X","ts":222,"pid":9036,"tid":0,"dur":1},{"name":"generate_text_token","cat":"function","ph":"X","ts":223,"pid":9036,"tid":0,"dur":1},{"name":"gen token newline","cat":"function","ph":"X","ts":223,"pid":9036,"tid":0,"dur":1},{"name":"generate_text_token","cat":"function","ph":"X","ts":224,"pid":9036,"tid":0,"dur":1},{"name":"gen token newline","cat":"function","ph":"X","ts":225,"pid":9036,"tid":0,"dur":1},{"name":"gen token newline","cat":"function","ph":"X","ts":225,"pid":9036,"tid":0,"dur":1},{"name":"generate_text_token","cat":"function","ph":"X","ts":226,"pid":9036,"tid":0,"dur":1},{"name":"generate_text_token","cat":"function","ph":"X","ts":227,"pid":9036,"tid":0,"dur":1},{"name":"gen TokenTypeOperatorEqual","cat":"function","ph":"X","ts":227,"pid":9036,"tid":0,"dur":1},{"name":"generate_text_token","cat":"function","ph":"X","ts":228,"pid":9036,"tid":0,"dur":1},{"name":"gen token separator","cat":"function","ph":"X","ts":229,"pid":9036,"tid":0,"dur":1},{"name":"generate_text_token","cat":"function","ph":"X","ts":229,"pid":9036,"tid":0,"dur":1},{"name":"gen token separator","cat":"function","ph":"X","ts":230,"pid":9036,"tid":0,"dur":1},{"name":"generate_number_literal_token","cat":"function","ph":"X","ts":231,"pid":9036,"tid":0,"dur":1},{"name":"gen token separator","cat":"function","ph":"X","ts":231,"pid":9036,"tid":0,"dur":1},{"name":"gen token separator","cat":"function","ph":"X","ts":232,"pid":9036,"tid":0,"dur":1},{"name":"gen token newline","cat":"function","ph":"X","ts":232,"pid":9036,"tid":0,"dur":1},{"name":"generate_text_token","cat":"function","ph":"X","ts":233,"pid":9036,"tid":0,"dur":1},{"name":"gen '='","cat":"function","ph":"X","ts":234,"pid":9036,"tid":0,"dur":1},{"name":"generate_number_literal_token","cat":"function","ph":"X","ts":234,"pid":9036,"tid":0,"dur":1},{"name":"gen token newline","cat":"function","ph":"X","ts":235,"pid":9036,"tid":0,"dur":1},{"name":"gen token newline","cat":"function","ph":"X","ts":236,"pid":9036,"tid":0,"dur":1},{"name":"generate_text_token","cat":"function","ph":"X","ts":236,"pid":9036,"tid":0,"dur":1},{"name":"generate_text_token","cat":"function","ph":"X","ts":237,"pid":9036,"tid":0,"dur":1},{"name":"gen token separator","cat":"function","ph":"X","ts":238,"pid":9036,"tid":0,"dur":1},{"name":"generate_text_token","cat":"function","ph":"X","ts":238,"pid":9036,"tid":0,"dur":1},{"name":"gen token separator","cat":"function","ph":"X","ts":239,"pid":9036,"tid":0,"dur":1},{"name":"generate_text_token","cat":"function","ph":"X","ts":240,"pid":9036,"tid":0,"dur":1},{"name":"gen token separator","cat":"function","ph":"X","ts":240,"pid":9036,"tid":0,"dur":1},{"name":"gen token newline","cat":"function","ph":"X","ts":241,"pid":9036,"tid":0,"dur":1},{"name":"generate_text_token","cat":"function","ph":"X","ts":242,"pid":9036,"tid":0,"dur":1},{"name":"generate_text_token","cat":"function","ph":"X","ts":242,"pid":9036,"tid":0,"dur":1},{"name":"gen TokenTypeOperatorEqual","cat":"function","ph":"X","ts":243,"pid":9036,"tid":0,"dur":1},{"name":"generate_text_token","cat":"function","ph":"X","ts":243,"pid":9036,"tid":0,"dur":1},{"name":"gen TokenTypeAssignmentPlus","cat":"function","ph":"X","ts":244,"pid":9036,"tid":0,"dur":1},{"name":"generate_text_token","cat":"function","ph":"X","ts":245,"pid":9036,"tid":0,"dur":1},{"name":"gen token newline","cat":"function","ph":"X","ts":246,"pid":9036,"tid":0,"dur":1},{"name":"generate_text_token","cat":"function","ph":"X","ts":246,"pid":9036,"tid":0,"dur":1},{"name":"generate_text_token","cat":"function","ph":"X","ts":247,"pid":9036,"tid":0,"dur":1},{"name":"gen token newline","cat":"function","ph":"X","ts":247,"pid":9036,"tid":0,"dur":1},{"name":"generate_text_token","cat":"function","ph":"X","ts":249,"pid":9036,"tid":0,"dur":1},{"name":"gen token newline","cat":"function","ph":"X","ts":250,"pid":9036,"tid":0,"dur":1},{"name":"generate_text_token","cat":"function","ph":"X","ts":250,"pid":9036,"tid":0,"dur":1},{"name":"generate_text_token","cat":"function","ph":"X","ts":251,"pid":9036,"tid":0,"dur":1},{"name":"gen TokenTypeOperatorEqual","cat":"function","ph":"X","ts":252,"pid":9036,"tid":0,"dur":1},{"name":"generate_text_token","cat":"function","ph":"X","ts":252,"pid":9036,"tid":0,"dur":1},{"name":"gen token separator","cat":"function","ph":"X","ts":253,"pid":9036,"tid":0,"dur":1},{"name":"generate_text_token","cat":"function","ph":"X","ts":254,"pid":9036,"tid":0,"dur":1},{"name":"gen token separator","cat":"function","ph":"X","ts":255,"pid":9036,"tid":0,"dur":1},{"name":"generate_number_literal_token","cat":"function","ph":"X","ts":255,"pid":9036,"tid":0,"dur":1},{"name":"gen token separator","cat":"function","ph":"X","ts":256,"pid":9036,"tid":0,"dur":1},{"name":"generate_number_literal_token","cat":"function","ph":"X","ts":256,"pid":9036,"tid":0,"dur":1},{"name":"gen token separator","cat":"function","ph":"X","ts":257,"pid":9036,"tid":0,"dur":1},{"name":"gen token separator","cat":"function","ph":"X","ts":258,"pid":9036,"tid":0,"dur":1},{"name":"generate_text_token","cat":"function","ph":"X","ts":258,"pid":9036,"tid":0,"dur":1},{"name":"gen token separator","cat":"function","ph":"X","ts":259,"pid":9036,"tid":0,"dur":1},{"name":"generate_number_literal_token","cat":"function","ph":"X","ts":259,"pid":9036,"tid":0,"dur":1},{"name":"gen token separator","cat":"function","ph":"X","ts":260,"pid":9036,"tid":0,"dur":1},{"name":"generate_number_literal_token","cat":"function","ph":"X","ts":261,"pid":9036,"tid":0,"dur":1},{"name":"gen token separator","cat":"function","ph":"X","ts":261,"pid":9036,"tid":0,"dur":1},{"name":"gen token separator","cat":"function","ph":"X","ts":262,"pid":9036,"tid":0,"dur":1},{"name":"gen token newline","cat":"function","ph":"X","ts":262,"pid":9036,"tid":0,"dur":1},{"name":"generate_text_token","cat":"function","ph":"X","ts":263,"pid":9036,"tid":0,"dur":1},{"name":"gen '='","cat":"function","ph":"X","ts":264,"pid":9036,"tid":0,"dur":1},{"name":"generate_number_literal_token","cat":"function","ph":"X","ts":264,"pid":9036,"tid":0,"dur":1},{"name":"generate_tokens","cat":"function","ph":"X","ts":95,"pid":9036,"tid":0,"dur":169},{"name":"init_parser","cat":"function","ph":"X","ts":270,"pid":9036,"tid":0,"dur":1},{"name":"make_ast_node","cat":"function","ph":"X","ts":276,"pid":9036,"tid":0,"dur":1},{"name":"parse_identifier","cat":"function","ph":"X","ts":277,"pid":9036,"tid":0,"dur":1},{"name":"make_ast_node","cat":"function","ph":"X","ts":278,"pid":9036,"tid":0,"dur":1},{"name":"parse_term","cat":"function","ph":"X","ts":278,"pid":9036,"tid":0,"dur":1},{"name":"make_ast_node","cat":"function","ph":"X","ts":279,"pid":9036,"tid":0,"dur":1},{"name":"make_ast_node","cat":"function","ph":"X","ts":280,"pid":9036,"tid":0,"dur":1},{"name":"parse_term","cat":"function","ph":"X","ts":280,"pid":9036,"tid":0,"dur":1},{"name":"parse_term","cat":"function","ph":"X","ts":281,"pid":9036,"tid":0,"dur":1},{"name":"make_ast_node","cat":"function","ph":"X","ts":282,"pid":9036,"tid":0,"dur":1},{"name":"make_ast_node","cat":"function","ph":"X","ts":282,"pid":9036,"tid":0,"dur":1},{"name":"parse_term","cat":"function","ph":"X","ts":283,"pid":9036,"tid":0,"dur":1},{"name":"make_ast_node","cat":"function","ph":"X","ts":283,"pid":9036,"tid":0,"dur":1},{"name":"make_ast_node","cat":"function","ph":"X","ts":284,"pid":9036,"tid":0,"dur":1},{"name":"parse_term","cat":"function","ph":"X","ts":284,"pid":9036,"tid":0,"dur":1},{"name":"make_ast_node","cat":"function","ph":"X","ts":285,"pid":9036,"tid":0,"dur":1},{"name":"make_ast_node","cat":"function","ph":"X","ts":285,"pid":9036,"tid":0,"dur":1},{"name":"parse_term","cat":"function","ph":"X","ts":286,"pid":9036,"tid":0,"dur":1},{"name":"make_ast_node","cat":"function","ph":"X","ts":286,"pid":9036,"tid":0,"dur":1},{"name":"make_ast_node","cat":"function","ph":"X","ts":288,"pid":9036,"tid":0,"dur":1},{"name":"parse_term","cat":"function","ph":"X","ts":289,"pid":9036,"tid":0,"dur":1},{"name":"make_ast_node","cat":"function","ph":"X","ts":289,"pid":9036,"tid":0,"dur":1},{"name":"parse_expr","cat":"function","ph":"X","ts":282,"pid":9036,"tid":0,"dur":7},{"name":"expr_brackets_terminal","cat":"function","ph":"X","ts":290,"pid":9036,"tid":0,"dur":1},{"name":"make_ast_node","cat":"function","ph":"X","ts":291,"pid":9036,"tid":0,"dur":1},{"name":"parse_expr_with_brackets","cat":"function","ph":"X","ts":281,"pid":9036,"tid":0,"dur":10},{"name":"make_ast_node","cat":"function","ph":"X","ts":292,"pid":9036,"tid":0,"dur":1},{"name":"parse_term","cat":"function","ph":"X","ts":293,"pid":9036,"tid":0,"dur":1},{"name":"make_ast_node","cat":"function","ph":"X","ts":293,"pid":9036,"tid":0,"dur":1},{"name":"make_ast_node","cat":"function","ph":"X","ts":294,"pid":9036,"tid":0,"dur":1},{"name":"parse_term","cat":"function","ph":"X","ts":294,"pid":9036,"tid":0,"dur":1},{"name":"make_ast_node","cat":"function","ph":"X","ts":295,"pid":9036,"tid":0,"dur":1},{"name":"parse_expr","cat":"function","ph":"X","ts":280,"pid":9036,"tid":0,"dur":15},{"name":"parse_vardecl","cat":"function","ph":"X","ts":273,"pid":9036,"tid":0,"dur":22},{"name":"make_ast_node","cat":"function","ph":"X","ts":297,"pid":9036,"tid":0,"dur":1},{"name":"parse_identifier","cat":"function","ph":"X","ts":298,"pid":9036,"tid":0,"dur":1},{"name":"make_ast_node","cat":"function","ph":"X","ts":298,"pid":9036,"tid":0,"dur":1},{"name":"parse_term","cat":"function","ph":"X","ts":300,"pid":9036,"tid":0,"dur":1},{"name":"make_ast_node","cat":"function","ph":"X","ts":301,"pid":9036,"tid":0,"dur":1},{"name":"make_ast_node","cat":"function","ph":"X","ts":301,"pid":9036,"tid":0,"dur":1},{"name":"parse_term","cat":"function","ph":"X","ts":302,"pid":9036,"tid":0,"dur":1},{"name":"make_ast_node","cat":"function","ph":"X","ts":302,"pid":9036,"tid":0,"dur":1},{"name":"make_ast_node","cat":"function","ph":"X","ts":303,"pid":9036,"tid":0,"dur":1},{"name":"parse_term","cat":"function","ph":"X","ts":303,"pid":9036,"tid":0,"dur":1},{"name":"make_ast_node","cat":"function","ph":"X","ts":304,"pid":9036,"tid":0,"dur":1},{"name":"make_ast_node","cat":"function","ph":"X","ts":304,"pid":9036,"tid":0,"dur":1},{"name":"parse_term","cat":"function","ph":"X","ts":305,"pid":9036,"tid":0,"dur":1},{"name":"make_ast_node","cat":"function","ph":"X","ts":305,"pid":9036,"tid":0,"dur":1},{"name":"parse_expr","cat":"function","ph":"X","ts":301,"pid":9036,"tid":0,"dur":4},{"name":"parse_vardecl","cat":"function","ph":"X","ts":297,"pid":9036,"tid":0,"dur":9},{"name":"make_ast_node","cat":"function","ph":"X","ts":314,"pid":9036,"tid":0,"dur":1},{"name":"parse_identifier","cat":"function","ph":"X","ts":315,"pid":9036,"tid":0,"dur":1},{"name":"make_ast_node","cat":"function","ph":"X","ts":315,"pid":9036,"tid":0,"dur":1},{"name":"parse_term","cat":"function","ph":"X","ts":316,"pid":9036,"tid":0,"dur":1},{"name":"make_ast_node","cat":"function","ph":"X","ts":316,"pid":9036,"tid":0,"dur":1},{"name":"make_ast_node","cat":"function","ph":"X","ts":317,"pid":9036,"tid":0,"dur":1},{"name":"parse_term","cat":"function","ph":"X","ts":317,"pid":9036,"tid":0,"dur":1},{"name":"make_ast_node","cat":"function","ph":"X","ts":318,"pid":9036,"tid":0,"dur":1},{"name":"make_ast_node","cat":"function","ph":"X","ts":318,"pid":9036,"tid":0,"dur":1},{"name":"parse_term","cat":"function","ph":"X","ts":319,"pid":9036,"tid":0,"dur":1},{"name":"make_ast_node","cat":"function","ph":"X","ts":319,"pid":9036,"tid":0,"dur":1},{"name":"make_ast_node","cat":"function","ph":"X","ts":320,"pid":9036,"tid":0,"dur":1},{"name":"make_ast_node","cat":"function","ph":"X","ts":320,"pid":9036,"tid":0,"dur":1},{"name":"parse_term","cat":"function","ph":"X","ts":321,"pid":9036,"tid":0,"dur":1},{"name":"make_ast_node","cat":"function","ph":"X","ts":321,"pid":9036,"tid":0,"dur":1},{"name":"make_ast_node","cat":"function","ph":"X","ts":322,"pid":9036,"tid":0,"dur":1},{"name":"parse_term","cat":"function","ph":"X","ts":323,"pid":9036,"tid":0,"dur":1},{"name":"make_ast_node","cat":"function","ph":"X","ts":324,"pid":9036,"tid":0,"dur":1},{"name":"make_ast_node","cat":"function","ph":"X","ts":325,"pid":9036,"tid":0,"dur":1},{"name":"parse_term","cat":"function","ph":"X","ts":326,"pid":9036,"tid":0,"dur":1},{"name":"make_ast_node","cat":"function","ph":"X","ts":326,"pid":9036,"tid":0,"dur":1},{"name":"parse_expr","cat":"function","ph":"X","ts":317,"pid":9036,"tid":0,"dur":9},{"name":"parse_vardecl","cat":"function","ph":"X","ts":314,"pid":9036,"tid":0,"dur":13},{"name":"make_ast_node","cat":"function","ph":"X","ts":328,"pid":9036,"tid":0,"dur":1},{"name":"parse_identifier","cat":"function","ph":"X","ts":328,"pid":9036,"tid":0,"dur":1},{"name":"make_ast_node","cat":"function","ph":"X","ts":329,"pid":9036,"tid":0,"dur":1},{"name":"parse_term","cat":"function","ph":"X","ts":329,"pid":9036,"tid":0,"dur":1},{"name":"make_ast_node","cat":"function","ph":"X","ts":330,"pid":9036,"tid":0,"dur":1},{"name":"parse_rvalue","cat":"function","ph":"X","ts":330,"pid":9036,"tid":0,"dur":1},{"name":"make_ast_node","cat":"function","ph":"X","ts":331,"pid":9036,"tid":0,"dur":1},{"name":"parse_term","cat":"function","ph":"X","ts":332,"pid":9036,"tid":0,"dur":1},{"name":"make_ast_node","cat":"function","ph":"X","ts":332,"pid":9036,"tid":0,"dur":1},{"name":"parse_rvalue","cat":"function","ph":"X","ts":332,"pid":9036,"tid":0,"dur":1},{"name":"make_ast_node","cat":"function","ph":"X","ts":333,"pid":9036,"tid":0,"dur":1},{"name":"parse_term","cat":"function","ph":"X","ts":334,"pid":9036,"tid":0,"dur":1},{"name":"make_ast_node","cat":"function","ph":"X","ts":334,"pid":9036,"tid":0,"dur":1},{"name":"parse_rvalue","cat":"function","ph":"X","ts":334,"pid":9036,"tid":0,"dur":1},{"name":"parse_expr","cat":"function","ph":"X","ts":331,"pid":9036,"tid":0,"dur":4},{"name":"parse_vardecl","cat":"function","ph":"X","ts":328,"pid":9036,"tid":0,"dur":8},{"name":"make_ast_node","cat":"function","ph":"X","ts":337,"pid":9036,"tid":0,"dur":1},{"name":"parse_identifier","cat":"function","ph":"X","ts":337,"pid":9036,"tid":0,"dur":1},{"name":"make_ast_node","cat":"function","ph":"X","ts":338,"pid":9036,"tid":0,"dur":1},{"name":"parse_term","cat":"function","ph":"X","ts":338,"pid":9036,"tid":0,"dur":1},{"name":"parse_term","cat":"function","ph":"X","ts":339,"pid":9036,"tid":0,"dur":1},{"name":"make_ast_node","cat":"function","ph":"X","ts":339,"pid":9036,"tid":0,"dur":1},{"name":"make_ast_node","cat":"function","ph":"X","ts":340,"pid":9036,"tid":0,"dur":1},{"name":"parse_term","cat":"function","ph":"X","ts":340,"pid":9036,"tid":0,"dur":1},{"name":"make_ast_node","cat":"function","ph":"X","ts":341,"pid":9036,"tid":0,"dur":1},{"name":"make_ast_node","cat":"function","ph":"X","ts":341,"pid":9036,"tid":0,"dur":1},{"name":"parse_term","cat":"function","ph":"X","ts":342,"pid":9036,"tid":0,"dur":1},{"name":"parse_term","cat":"function","ph":"X","ts":343,"pid":9036,"tid":0,"dur":1},{"name":"make_ast_node","cat":"function","ph":"X","ts":343,"pid":9036,"tid":0,"dur":1},{"name":"make_ast_node","cat":"function","ph":"X","ts":344,"pid":9036,"tid":0,"dur":1},{"name":"parse_term","cat":"function","ph":"X","ts":344,"pid":9036,"tid":0,"dur":1},{"name":"parse_term","cat":"function","ph":"X","ts":345,"pid":9036,"tid":0,"dur":1},{"name":"make_ast_node","cat":"function","ph":"X","ts":345,"pid":9036,"tid":0,"dur":1},{"name":"make_ast_node","cat":"function","ph":"X","ts":346,"pid":9036,"tid":0,"dur":1},{"name":"parse_term","cat":"function","ph":"X","ts":347,"pid":9036,"tid":0,"dur":1},{"name":"make_ast_node","cat":"function","ph":"X","ts":347,"pid":9036,"tid":0,"dur":1},{"name":"parse_expr","cat":"function","ph":"X","ts":346,"pid":9036,"tid":0,"dur":1},{"name":"expr_brackets_terminal","cat":"function","ph":"X","ts":348,"pid":9036,"tid":0,"dur":1},{"name":"make_ast_node","cat":"function","ph":"X","ts":349,"pid":9036,"tid":0,"dur":1},{"name":"parse_expr_with_brackets","cat":"function","ph":"X","ts":345,"pid":9036,"tid":0,"dur":4},{"name":"parse_expr","cat":"function","ph":"X","ts":344,"pid":9036,"tid":0,"dur":6},{"name":"expr_brackets_terminal","cat":"function","ph":"X","ts":350,"pid":9036,"tid":0,"dur":1},{"name":"make_ast_node","cat":"function","ph":"X","ts":351,"pid":9036,"tid":0,"dur":1},{"name":"parse_expr_with_brackets","cat":"function","ph":"X","ts":343,"pid":9036,"tid":0,"dur":8},{"name":"make_ast_node","cat":"function","ph":"X","ts":352,"pid":9036,"tid":0,"dur":1},{"name":"parse_term","cat":"function","ph":"X","ts":353,"pid":9036,"tid":0,"dur":1},{"name":"make_ast_node","cat":"function","ph":"X","ts":353,"pid":9036,"tid":0,"dur":1},{"name":"make_ast_node","cat":"function","ph":"X","ts":354,"pid":9036,"tid":0,"dur":1},{"name":"parse_term","cat":"function","ph":"X","ts":354,"pid":9036,"tid":0,"dur":1},{"name":"make_ast_node","cat":"function","ph":"X","ts":355,"pid":9036,"tid":0,"dur":1},{"name":"make_ast_node","cat":"function","ph":"X","ts":355,"pid":9036,"tid":0,"dur":1},{"name":"parse_term","cat":"function","ph":"X","ts":356,"pid":9036,"tid":0,"dur":1},{"name":"make_ast_node","cat":"function","ph":"X","ts":356,"pid":9036,"tid":0,"dur":1},{"name":"parse_expr","cat":"function","ph":"X","ts":340,"pid":9036,"tid":0,"dur":16},{"name":"expr_brackets_terminal","cat":"function","ph":"X","ts":357,"pid":9036,"tid":0,"dur":1},{"name":"make_ast_node","cat":"function","ph":"X","ts":358,"pid":9036,"tid":0,"dur":1},{"name":"parse_expr_with_brackets","cat":"function","ph":"X","ts":339,"pid":9036,"tid":0,"dur":19},{"name":"make_ast_node","cat":"function","ph":"X","ts":359,"pid":9036,"tid":0,"dur":1},{"name":"parse_term","cat":"function","ph":"X","ts":359,"pid":9036,"tid":0,"dur":1},{"name":"make_ast_node","cat":"function","ph":"X","ts":360,"pid":9036,"tid":0,"dur":1},{"name":"make_ast_node","cat":"function","ph":"X","ts":360,"pid":9036,"tid":0,"dur":1},{"name":"parse_term","cat":"function","ph":"X","ts":361,"pid":9036,"tid":0,"dur":1},{"name":"parse_term","cat":"function","ph":"X","ts":361,"pid":9036,"tid":0,"dur":1},{"name":"fetching trace data","cat":"function","ph":"X","ts":362,"pid":9036,"tid":0,"dur":251},{"name":"make_ast_node","cat":"function","ph":"X","ts":362,"pid":9036,"tid":0,"dur":1},{"name":"make_ast_node","cat":"function","ph":"X","ts":615,"pid":9036,"tid":0,"dur":1},{"name":"parse_term","cat":"function","ph":"X","ts":616,"pid":9036,"tid":0,"dur":1},{"name":"make_ast_node","cat":"function","ph":"X","ts":617,"pid":9036,"tid":0,"dur":1},{"name":"parse_expr","cat":"function","ph":"X","ts":615,"pid":9036,"tid":0,"dur":2},{"name":"expr_brackets_terminal","cat":"function","ph":"X","ts":618,"pid":9036,"tid":0,"dur":1},{"name":"make_ast_node","cat":"function","ph":"X","ts":619,"pid":9036,"tid":0,"dur":1},{"name":"parse_expr_with_brackets","cat":"function","ph":"X","ts":361,"pid":9036,"tid":0,"dur":257},{"name":"make_ast_node","cat":"function","ph":"X","ts":620,"pid":9036,"tid":0,"dur":1},{"name":"parse_term","cat":"function","ph":"X","ts":621,"pid":9036,"tid":0,"dur":1},{"name":"parse_term","cat":"function","ph":"X","ts":621,"pid":9036,"tid":0,"dur":1},{"name":"make_ast_node","cat":"function","ph":"X","ts":622,"pid":9036,"tid":0,"dur":1},{"name":"make_ast_node","cat":"function","ph":"X","ts":622,"pid":9036,"tid":0,"dur":1},{"name":"parse_term","cat":"function","ph":"X","ts":623,"pid":9036,"tid":0,"dur":1},{"name":"make_ast_node","cat":"function","ph":"X","ts":623,"pid":9036,"tid":0,"dur":1},{"name":"make_ast_node","cat":"function","ph":"X","ts":624,"pid":9036,"tid":0,"dur":1},{"name":"parse_term","cat":"function","ph":"X","ts":624,"pid":9036,"tid":0,"dur":1},{"name":"make_ast_node","cat":"function","ph":"X","ts":625,"pid":9036,"tid":0,"dur":1},{"name":"parse_expr","cat":"function","ph":"X","ts":622,"pid":9036,"tid":0,"dur":3},{"name":"expr_brackets_terminal","cat":"function","ph":"X","ts":626,"pid":9036,"tid":0,"dur":1},{"name":"make_ast_node","cat":"function","ph":"X","ts":626,"pid":9036,"tid":0,"dur":1},{"name":"parse_expr_with_brackets","cat":"function","ph":"X","ts":621,"pid":9036,"tid":0,"dur":6},{"name":"parse_expr","cat":"function","ph":"X","ts":359,"pid":9036,"tid":0,"dur":268},{"name":"parse_vardecl","cat":"function","ph":"X","ts":337,"pid":9036,"tid":0,"dur":291},{"name":"make_ast_node","cat":"function","ph":"X","ts":630,"pid":9036,"tid":0,"dur":1},{"name":"parse_rvalue","cat":"function","ph":"X","ts":630,"pid":9036,"tid":0,"dur":1},{"name":"parse_reference","cat":"function","ph":"X","ts":630,"pid":9036,"tid":0,"dur":1},{"name":"make_ast_node","cat":"function","ph":"X","ts":632,"pid":9036,"tid":0,"dur":1},{"name":"parse_term","cat":"function","ph":"X","ts":632,"pid":9036,"tid":0,"dur":1},{"name":"make_ast_node","cat":"function","ph":"X","ts":633,"pid":9036,"tid":0,"dur":1},{"name":"parse_expr","cat":"function","ph":"X","ts":633,"pid":9036,"tid":0,"dur":1},{"name":"parse_identifier_statement","cat":"function","ph":"X","ts":630,"pid":9036,"tid":0,"dur":3},{"name":"make_ast_node","cat":"function","ph":"X","ts":634,"pid":9036,"tid":0,"dur":1},{"name":"parse_rvalue","cat":"function","ph":"X","ts":634,"pid":9036,"tid":0,"dur":1},{"name":"parse_reference","cat":"function","ph":"X","ts":634,"pid":9036,"tid":0,"dur":1},{"name":"make_ast_node","cat":"function","ph":"X","ts":636,"pid":9036,"tid":0,"dur":1},{"name":"parse_term","cat":"function","ph":"X","ts":637,"pid":9036,"tid":0,"dur":1},{"name":"make_ast_node","cat":"function","ph":"X","ts":637,"pid":9036,"tid":0,"dur":1},{"name":"parse_rvalue","cat":"function","ph":"X","ts":637,"pid":9036,"tid":0,"dur":1},{"name":"parse_expr","cat":"function","ph":"X","ts":638,"pid":9036,"tid":0,"dur":1},{"name":"parse_identifier_statement","cat":"function","ph":"X","ts":634,"pid":9036,"tid":0,"dur":4},{"name":"make_ast_node","cat":"function","ph":"X","ts":639,"pid":9036,"tid":0,"dur":1},{"name":"parse_rvalue","cat":"function","ph":"X","ts":639,"pid":9036,"tid":0,"dur":1},{"name":"parse_reference","cat":"function","ph":"X","ts":639,"pid":9036,"tid":0,"dur":1},{"name":"make_ast_node","cat":"function","ph":"X","ts":641,"pid":9036,"tid":0,"dur":1},{"name":"parse_term","cat":"function","ph":"X","ts":641,"pid":9036,"tid":0,"dur":1},{"name":"make_ast_node","cat":"function","ph":"X","ts":642,"pid":9036,"tid":0,"dur":1},{"name":"parse_rvalue","cat":"function","ph":"X","ts":642,"pid":9036,"tid":0,"dur":1},{"name":"parse_expr","cat":"function","ph":"X","ts":643,"pid":9036,"tid":0,"dur":1},{"name":"parse_identifier_statement","cat":"function","ph":"X","ts":639,"pid":9036,"tid":0,"dur":4},{"name":"make_ast_node","cat":"function","ph":"X","ts":644,"pid":9036,"tid":0,"dur":1},{"name":"parse_rvalue","cat":"function","ph":"X","ts":644,"pid":9036,"tid":0,"dur":1},{"name":"parse_reference","cat":"function","ph":"X","ts":644,"pid":9036,"tid":0,"dur":1},{"name":"make_ast_node","cat":"function","ph":"X","ts":646,"pid":9036,"tid":0,"dur":3},{"name":"parse_term","cat":"function","ph":"X","ts":650,"pid":9036,"tid":0,"dur":1},{"name":"make_ast_node","cat":"function","ph":"X","ts":650,"pid":9036,"tid":0,"dur":1},{"name":"parse_rvalue","cat":"function","ph":"X","ts":650,"pid":9036,"tid":0,"dur":1},{"name":"parse_expr","cat":"function","ph":"X","ts":651,"pid":9036,"tid":0,"dur":1},{"name":"parse_identifier_statement","cat":"function","ph":"X","ts":644,"pid":9036,"tid":0,"dur":7},{"name":"make_ast_node","cat":"function","ph":"X","ts":653,"pid":9036,"tid":0,"dur":1},{"name":"parse_rvalue","cat":"function","ph":"X","ts":653,"pid":9036,"tid":0,"dur":1},{"name":"parse_reference","cat":"function","ph":"X","ts":653,"pid":9036,"tid":0,"dur":1},{"name":"make_ast_node","cat":"function","ph":"X","ts":654,"pid":9036,"tid":0,"dur":1},{"name":"parse_term","cat":"function","ph":"X","ts":655,"pid":9036,"tid":0,"dur":1},{"name":"make_ast_node","cat":"function","ph":"X","ts":655,"pid":9036,"tid":0,"dur":1},{"name":"parse_rvalue","cat":"function","ph":"X","ts":655,"pid":9036,"tid":0,"dur":1},{"name":"parse_expr","cat":"function","ph":"X","ts":656,"pid":9036,"tid":0,"dur":1},{"name":"parse_identifier_statement","cat":"function","ph":"X","ts":652,"pid":9036,"tid":0,"dur":4},{"name":"make_ast_node","cat":"function","ph":"X","ts":657,"pid":9036,"tid":0,"dur":1},{"name":"parse_rvalue","cat":"function","ph":"X","ts":657,"pid":9036,"tid":0,"dur":1},{"name":"parse_reference","cat":"function","ph":"X","ts":657,"pid":9036,"tid":0,"dur":1},{"name":"make_ast_node","cat":"function","ph":"X","ts":659,"pid":9036,"tid":0,"dur":1},{"name":"parse_term","cat":"function","ph":"X","ts":659,"pid":9036,"tid":0,"dur":1},{"name":"make_ast_node","cat":"function","ph":"X","ts":660,"pid":9036,"tid":0,"dur":1},{"name":"parse_rvalue","cat":"function","ph":"X","ts":660,"pid":9036,"tid":0,"dur":1},{"name":"parse_expr","cat":"function","ph":"X","ts":661,"pid":9036,"tid":0,"dur":1},{"name":"parse_identifier_statement","cat":"function","ph":"X","ts":657,"pid":9036,"tid":0,"dur":4},{"name":"make_ast_node","cat":"function","ph":"X","ts":662,"pid":9036,"tid":0,"dur":1},{"name":"parse_rvalue","cat":"function","ph":"X","ts":662,"pid":9036,"tid":0,"dur":1},{"name":"make_ast_node","cat":"function","ph":"X","ts":663,"pid":9036,"tid":0,"dur":1},{"name":"parse_rvalue_access","cat":"function","ph":"X","ts":663,"pid":9036,"tid":0,"dur":1},{"name":"parse_reference","cat":"function","ph":"X","ts":662,"pid":9036,"tid":0,"dur":2},{"name":"parse_identifier_statement","cat":"function","ph":"X","ts":662,"pid":9036,"tid":0,"dur":2},{"name":"make_ast_node","cat":"function","ph":"X","ts":665,"pid":9036,"tid":0,"dur":1},{"name":"make_ast_node","cat":"function","ph":"X","ts":666,"pid":9036,"tid":0,"dur":1},{"name":"parse_rvalue","cat":"function","ph":"X","ts":666,"pid":9036,"tid":0,"dur":1},{"name":"make_ast_node","cat":"function","ph":"X","ts":667,"pid":9036,"tid":0,"dur":1},{"name":"parse_rvalue_access","cat":"function","ph":"X","ts":667,"pid":9036,"tid":0,"dur":1},{"name":"make_ast_node","cat":"function","ph":"X","ts":668,"pid":9036,"tid":0,"dur":1},{"name":"parse_rvalue_access","cat":"function","ph":"X","ts":668,"pid":9036,"tid":0,"dur":1},{"name":"parse_reference","cat":"function","ph":"X","ts":666,"pid":9036,"tid":0,"dur":3},{"name":"parse_identifier_statement","cat":"function","ph":"X","ts":666,"pid":9036,"tid":0,"dur":3},{"name":"make_ast_node","cat":"function","ph":"X","ts":670,"pid":9036,"tid":0,"dur":1},{"name":"make_ast_node","cat":"function","ph":"X","ts":671,"pid":9036,"tid":0,"dur":1},{"name":"parse_rvalue","cat":"function","ph":"X","ts":671,"pid":9036,"tid":0,"dur":1},{"name":"make_ast_node","cat":"function","ph":"X","ts":672,"pid":9036,"tid":0,"dur":1},{"name":"parse_rvalue_access","cat":"function","ph":"X","ts":672,"pid":9036,"tid":0,"dur":1},{"name":"make_ast_node","cat":"function","ph":"X","ts":673,"pid":9036,"tid":0,"dur":1},{"name":"parse_rvalue_access","cat":"function","ph":"X","ts":673,"pid":9036,"tid":0,"dur":1},{"name":"make_ast_node","cat":"function","ph":"X","ts":674,"pid":9036,"tid":0,"dur":1},{"name":"parse_rvalue_access","cat":"function","ph":"X","ts":674,"pid":9036,"tid":0,"dur":1},{"name":"parse_reference","cat":"function","ph":"X","ts":671,"pid":9036,"tid":0,"dur":4},{"name":"parse_identifier_statement","cat":"function","ph":"X","ts":671,"pid":9036,"tid":0,"dur":4},{"name":"make_ast_node","cat":"function","ph":"X","ts":676,"pid":9036,"tid":0,"dur":1},{"name":"make_ast_node","cat":"function","ph":"X","ts":678,"pid":9036,"tid":0,"dur":1},{"name":"parse_rvalue","cat":"function","ph":"X","ts":678,"pid":9036,"tid":0,"dur":1},{"name":"make_ast_node","cat":"function","ph":"X","ts":679,"pid":9036,"tid":0,"dur":1},{"name":"parse_rvalue_access","cat":"function","ph":"X","ts":679,"pid":9036,"tid":0,"dur":1},{"name":"make_ast_node","cat":"function","ph":"X","ts":680,"pid":9036,"tid":0,"dur":1},{"name":"parse_rvalue_access","cat":"function","ph":"X","ts":680,"pid":9036,"tid":0,"dur":1},{"name":"make_ast_node","cat":"function","ph":"X","ts":681,"pid":9036,"tid":0,"dur":1},{"name":"parse_rvalue_access","cat":"function","ph":"X","ts":681,"pid":9036,"tid":0,"dur":1},{"name":"make_ast_node","cat":"function","ph":"X","ts":682,"pid":9036,"tid":0,"dur":1},{"name":"parse_rvalue_access","cat":"function","ph":"X","ts":682,"pid":9036,"tid":0,"dur":1},{"name":"parse_reference","cat":"function","ph":"X","ts":678,"pid":9036,"tid":0,"dur":5},{"name":"parse_identifier_statement","cat":"function","ph":"X","ts":678,"pid":9036,"tid":0,"dur":5},{"name":"make_ast_node","cat":"function","ph":"X","ts":684,"pid":9036,"tid":0,"dur":1},{"name":"make_ast_node","cat":"function","ph":"X","ts":685,"pid":9036,"tid":0,"dur":1},{"name":"make_ast_node","cat":"function","ph":"X","ts":685,"pid":9036,"tid":0,"dur":1},{"name":"make_ast_node","cat":"function","ph":"X","ts":686,"pid":9036,"tid":0,"dur":1},{"name":"make_ast_node","cat":"function","ph":"X","ts":686,"pid":9036,"tid":0,"dur":1},{"name":"parse_identifier","cat":"function","ph":"X","ts":687,"pid":9036,"tid":0,"dur":1},{"name":"make_ast_node","cat":"function","ph":"X","ts":688,"pid":9036,"tid":0,"dur":1},{"name":"parse_term","cat":"function","ph":"X","ts":688,"pid":9036,"tid":0,"dur":1},{"name":"make_ast_node","cat":"function","ph":"X","ts":689,"pid":9036,"tid":0,"dur":1},{"name":"parse_rvalue","cat":"function","ph":"X","ts":689,"pid":9036,"tid":0,"dur":1},{"name":"make_ast_node","cat":"function","ph":"X","ts":690,"pid":9036,"tid":0,"dur":1},{"name":"parse_term","cat":"function","ph":"X","ts":690,"pid":9036,"tid":0,"dur":1},{"name":"make_ast_node","cat":"function","ph":"X","ts":691,"pid":9036,"tid":0,"dur":1},{"name":"parse_rvalue","cat":"function","ph":"X","ts":691,"pid":9036,"tid":0,"dur":1},{"name":"parse_expr","cat":"function","ph":"X","ts":690,"pid":9036,"tid":0,"dur":2},{"name":"parse_vardecl","cat":"function","ph":"X","ts":686,"pid":9036,"tid":0,"dur":5},{"name":"make_ast_node","cat":"function","ph":"X","ts":693,"pid":9036,"tid":0,"dur":1},{"name":"parse_term","cat":"function","ph":"X","ts":693,"pid":9036,"tid":0,"dur":1},{"name":"make_ast_node","cat":"function","ph":"X","ts":694,"pid":9036,"tid":0,"dur":1},{"name":"parse_rvalue","cat":"function","ph":"X","ts":694,"pid":9036,"tid":0,"dur":1},{"name":"parse_expr","cat":"function","ph":"X","ts":695,"pid":9036,"tid":0,"dur":1},{"name":"make_ast_node","cat":"function","ph":"X","ts":696,"pid":9036,"tid":0,"dur":1},{"name":"make_ast_node","cat":"function","ph":"X","ts":696,"pid":9036,"tid":0,"dur":1},{"name":"parse_identifier","cat":"function","ph":"X","ts":697,"pid":9036,"tid":0,"dur":1},{"name":"make_ast_node","cat":"function","ph":"X","ts":697,"pid":9036,"tid":0,"dur":1},{"name":"parse_term","cat":"function","ph":"X","ts":698,"pid":9036,"tid":0,"dur":1},{"name":"make_ast_node","cat":"function","ph":"X","ts":698,"pid":9036,"tid":0,"dur":1},{"name":"make_ast_node","cat":"function","ph":"X","ts":699,"pid":9036,"tid":0,"dur":1},{"name":"parse_term","cat":"function","ph":"X","ts":700,"pid":9036,"tid":0,"dur":1},{"name":"make_ast_node","cat":"function","ph":"X","ts":700,"pid":9036,"tid":0,"dur":1},{"name":"make_ast_node","cat":"function","ph":"X","ts":701,"pid":9036,"tid":0,"dur":1},{"name":"parse_term","cat":"function","ph":"X","ts":701,"pid":9036,"tid":0,"dur":1},{"name":"make_ast_node","cat":"function","ph":"X","ts":702,"pid":9036,"tid":0,"dur":1},{"name":"parse_expr","cat":"function","ph":"X","ts":702,"pid":9036,"tid":0,"dur":1},{"name":"parse_argument","cat":"function","ph":"X","ts":701,"pid":9036,"tid":0,"dur":2},{"name":"make_ast_node","cat":"function","ph":"X","ts":703,"pid":9036,"tid":0,"dur":1},{"name":"parse_rvalue","cat":"function","ph":"X","ts":700,"pid":9036,"tid":0,"dur":3},{"name":"parse_expr","cat":"function","ph":"X","ts":704,"pid":9036,"tid":0,"dur":1},{"name":"parse_argument","cat":"function","ph":"X","ts":699,"pid":9036,"tid":0,"dur":6},{"name":"make_ast_node","cat":"function","ph":"X","ts":705,"pid":9036,"tid":0,"dur":1},{"name":"parse_rvalue","cat":"function","ph":"X","ts":698,"pid":9036,"tid":0,"dur":7},{"name":"parse_expr","cat":"function","ph":"X","ts":707,"pid":9036,"tid":0,"dur":1},{"name":"parse_vardecl","cat":"function","ph":"X","ts":696,"pid":9036,"tid":0,"dur":10},{"name":"make_ast_node","cat":"function","ph":"X","ts":708,"pid":9036,"tid":0,"dur":1},{"name":"parse_rvalue","cat":"function","ph":"X","ts":708,"pid":9036,"tid":0,"dur":1},{"name":"parse_reference","cat":"function","ph":"X","ts":708,"pid":9036,"tid":0,"dur":1},{"name":"make_ast_node","cat":"function","ph":"X","ts":709,"pid":9036,"tid":0,"dur":1},{"name":"parse_term","cat":"function","ph":"X","ts":710,"pid":9036,"tid":0,"dur":1},{"name":"make_ast_node","cat":"function","ph":"X","ts":710,"pid":9036,"tid":0,"dur":1},{"name":"parse_expr","cat":"function","ph":"X","ts":711,"pid":9036,"tid":0,"dur":1},{"name":"parse_identifier_statement","cat":"function","ph":"X","ts":708,"pid":9036,"tid":0,"dur":3},{"name":"make_ast_node","cat":"function","ph":"X","ts":712,"pid":9036,"tid":0,"dur":1},{"name":"make_ast_node","cat":"function","ph":"X","ts":712,"pid":9036,"tid":0,"dur":1},{"name":"make_ast_node","cat":"function","ph":"X","ts":713,"pid":9036,"tid":0,"dur":1},{"name":"make_ast_node","cat":"function","ph":"X","ts":714,"pid":9036,"tid":0,"dur":1},{"name":"make_ast_node","cat":"function","ph":"X","ts":714,"pid":9036,"tid":0,"dur":1},{"name":"parse_identifier","cat":"function","ph":"X","ts":715,"pid":9036,"tid":0,"dur":1},{"name":"make_ast_node","cat":"function","ph":"X","ts":715,"pid":9036,"tid":0,"dur":1},{"name":"parse_term","cat":"function","ph":"X","ts":716,"pid":9036,"tid":0,"dur":1},{"name":"make_ast_node","cat":"function","ph":"X","ts":716,"pid":9036,"tid":0,"dur":1},{"name":"parse_rvalue","cat":"function","ph":"X","ts":716,"pid":9036,"tid":0,"dur":1},{"name":"make_ast_node","cat":"function","ph":"X","ts":717,"pid":9036,"tid":0,"dur":1},{"name":"parse_term","cat":"function","ph":"X","ts":718,"pid":9036,"tid":0,"dur":1},{"name":"make_ast_node","cat":"function","ph":"X","ts":718,"pid":9036,"tid":0,"dur":1},{"name":"parse_rvalue","cat":"function","ph":"X","ts":718,"pid":9036,"tid":0,"dur":1},{"name":"parse_expr","cat":"function","ph":"X","ts":717,"pid":9036,"tid":0,"dur":2},{"name":"parse_vardecl","cat":"function","ph":"X","ts":714,"pid":9036,"tid":0,"dur":5},{"name":"make_ast_node","cat":"function","ph":"X","ts":720,"pid":9036,"tid":0,"dur":1},{"name":"parse_term","cat":"function","ph":"X","ts":721,"pid":9036,"tid":0,"dur":1},{"name":"make_ast_node","cat":"function","ph":"X","ts":722,"pid":9036,"tid":0,"dur":1},{"name":"parse_rvalue","cat":"function","ph":"X","ts":722,"pid":9036,"tid":0,"dur":1},{"name":"parse_expr","cat":"function","ph":"X","ts":723,"pid":9036,"tid":0,"dur":1},{"name":"make_ast_node","cat":"function","ph":"X","ts":723,"pid":9036,"tid":0,"dur":9},{"name":"make_ast_node","cat":"function","ph":"X","ts":733,"pid":9036,"tid":0,"dur":1},{"name":"parse_identifier","cat":"function","ph":"X","ts":734,"pid":9036,"tid":0,"dur":1},{"name":"make_ast_node","cat":"function","ph":"X","ts":734,"pid":9036,"tid":0,"dur":1},{"name":"parse_term","cat":"function","ph":"X","ts":735,"pid":9036,"tid":0,"dur":1},{"name":"make_ast_node","cat":"function","ph":"X","ts":735,"pid":9036,"tid":0,"dur":1},{"name":"make_ast_node","cat":"function","ph":"X","ts":736,"pid":9036,"tid":0,"dur":1},{"name":"parse_term","cat":"function","ph":"X","ts":736,"pid":9036,"tid":0,"dur":1},{"name":"make_ast_node","cat":"function","ph":"X","ts":737,"pid":9036,"tid":0,"dur":1},{"name":"make_ast_node","cat":"function","ph":"X","ts":737,"pid":9036,"tid":0,"dur":1},{"name":"parse_term","cat":"function","ph":"X","ts":738,"pid":9036,"tid":0,"dur":1},{"name":"make_ast_node","cat":"function","ph":"X","ts":738,"pid":9036,"tid":0,"dur":1},{"name":"parse_expr","cat":"function","ph":"X","ts":739,"pid":9036,"tid":0,"dur":1},{"name":"make_ast_node","cat":"function","ph":"X","ts":739,"pid":9036,"tid":0,"dur":1},{"name":"parse_term","cat":"function","ph":"X","ts":740,"pid":9036,"tid":0,"dur":1},{"name":"make_ast_node","cat":"function","ph":"X","ts":741,"pid":9036,"tid":0,"dur":1},{"name":"parse_expr","cat":"function","ph":"X","ts":741,"pid":9036,"tid":0,"dur":1},{"name":"parse_argument","cat":"function","ph":"X","ts":737,"pid":9036,"tid":0,"dur":4},{"name":"make_ast_node","cat":"function","ph":"X","ts":742,"pid":9036,"tid":0,"dur":1},{"name":"parse_rvalue","cat":"function","ph":"X","ts":737,"pid":9036,"tid":0,"dur":5},{"name":"parse_expr","cat":"function","ph":"X","ts":743,"pid":9036,"tid":0,"dur":1},{"name":"make_ast_node","cat":"function","ph":"X","ts":744,"pid":9036,"tid":0,"dur":1},{"name":"parse_term","cat":"function","ph":"X","ts":744,"pid":9036,"tid":0,"dur":1},{"name":"make_ast_node","cat":"function","ph":"X","ts":745,"pid":9036,"tid":0,"dur":1},{"name":"make_ast_node","cat":"function","ph":"X","ts":745,"pid":9036,"tid":0,"dur":1},{"name":"parse_term","cat":"function","ph":"X","ts":746,"pid":9036,"tid":0,"dur":1},{"name":"make_ast_node","cat":"function","ph":"X","ts":746,"pid":9036,"tid":0,"dur":1},{"name":"parse_expr","cat":"function","ph":"X","ts":747,"pid":9036,"tid":0,"dur":1},{"name":"make_ast_node","cat":"function","ph":"X","ts":747,"pid":9036,"tid":0,"dur":1},{"name":"parse_term","cat":"function","ph":"X","ts":748,"pid":9036,"tid":0,"dur":1},{"name":"make_ast_node","cat":"function","ph":"X","ts":749,"pid":9036,"tid":0,"dur":1},{"name":"parse_expr","cat":"function","ph":"X","ts":749,"pid":9036,"tid":0,"dur":1},{"name":"parse_argument","cat":"function","ph":"X","ts":745,"pid":9036,"tid":0,"dur":4},{"name":"make_ast_node","cat":"function","ph":"X","ts":750,"pid":9036,"tid":0,"dur":1},{"name":"parse_rvalue","cat":"function","ph":"X","ts":745,"pid":9036,"tid":0,"dur":5},{"name":"parse_expr","cat":"function","ph":"X","ts":751,"pid":9036,"tid":0,"dur":1},{"name":"parse_argument","cat":"function","ph":"X","ts":736,"pid":9036,"tid":0,"dur":16},{"name":"make_ast_node","cat":"function","ph":"X","ts":752,"pid":9036,"tid":0,"dur":1},{"name":"parse_rvalue","cat":"function","ph":"X","ts":735,"pid":9036,"tid":0,"dur":17},{"name":"parse_expr","cat":"function","ph":"X","ts":753,"pid":9036,"tid":0,"dur":1},{"name":"parse_vardecl","cat":"function","ph":"X","ts":733,"pid":9036,"tid":0,"dur":20},{"name":"make_ast_node","cat":"function","ph":"X","ts":754,"pid":9036,"tid":0,"dur":1},{"name":"parse_rvalue","cat":"function","ph":"X","ts":754,"pid":9036,"tid":0,"dur":1},{"name":"parse_reference","cat":"function","ph":"X","ts":754,"pid":9036,"tid":0,"dur":1},{"name":"make_ast_node","cat":"function","ph":"X","ts":756,"pid":9036,"tid":0,"dur":1},{"name":"parse_term","cat":"function","ph":"X","ts":756,"pid":9036,"tid":0,"dur":1},{"name":"make_ast_node","cat":"function","ph":"X","ts":757,"pid":9036,"tid":0,"dur":1},{"name":"parse_expr","cat":"function","ph":"X","ts":757,"pid":9036,"tid":0,"dur":1},{"name":"parse_identifier_statement","cat":"function","ph":"X","ts":754,"pid":9036,"tid":0,"dur":3},{"name":"init_environment","cat":"function","ph":"X","ts":759,"pid":9036,"tid":0,"dur":87},{"name":"init_vm","cat":"function","ph":"X","ts":759,"pid":9036,"tid":0,"dur":88},{"name":"gen_bytecode_push_const","cat":"function","ph":"X","ts":857,"pid":9036,"tid":0,"dur":1},{"name":"gen_const","cat":"function","ph":"X","ts":858,"pid":9036,"tid":0,"dur":1},{"name":"gen_bytecode_push_const","cat":"function","ph":"X","ts":859,"pid":9036,"tid":0,"dur":1},{"name":"gen_const","cat":"function","ph":"X","ts":860,"pid":9036,"tid":0,"dur":1},{"name":"gen_bytecode_push_const","cat":"function","ph":"X","ts":860,"pid":9036,"tid":0,"dur":7},{"name":"gen_const","cat":"function","ph":"X","ts":868,"pid":9036,"tid":0,"dur":1},{"name":"gen_bytecode_sub","cat":"function","ph":"X","ts":869,"pid":9036,"tid":0,"dur":1},{"name":"gen_bytecode_push_const","cat":"function","ph":"X","ts":870,"pid":9036,"tid":0,"dur":1},{"name":"gen_const","cat":"function","ph":"X","ts":870,"pid":9036,"tid":0,"dur":3},{"name":"gen_bytecode_sub","cat":"function","ph":"X","ts":875,"pid":9036,"tid":0,"dur":1},{"name":"gen_bytecode_push_const","cat":"function","ph":"X","ts":875,"pid":9036,"tid":0,"dur":1},{"name":"gen_const","cat":"function","ph":"X","ts":876,"pid":9036,"tid":0,"dur":1},{"name":"gen_bytecode_sub","cat":"function","ph":"X","ts":877,"pid":9036,"tid":0,"dur":1},{"name":"gen_bytecode_push_const","cat":"function","ph":"X","ts":877,"pid":9036,"tid":0,"dur":1},{"name":"gen_const","cat":"function","ph":"X","ts":878,"pid":9036,"tid":0,"dur":1},{"name":"gen_bytecode_sub","cat":"function","ph":"X","ts":879,"pid":9036,"tid":0,"dur":1},{"name":"gen_bytecode_sub","cat":"function","ph":"X","ts":879,"pid":9036,"tid":0,"dur":1},{"name":"gen_bytecode_push_const","cat":"function","ph":"X","ts":880,"pid":9036,"tid":0,"dur":1},{"name":"gen_const","cat":"function","ph":"X","ts":880,"pid":9036,"tid":0,"dur":1},{"name":"gen_bytecode_sub","cat":"function","ph":"X","ts":881,"pid":9036,"tid":0,"dur":1},{"name":"gen_bytecode_push_const","cat":"function","ph":"X","ts":881,"pid":9036,"tid":0,"dur":1},{"name":"gen_const","cat":"function","ph":"X","ts":882,"pid":9036,"tid":0,"dur":1},{"name":"gen_bytecode_sub","cat":"function","ph":"X","ts":883,"pid":9036,"tid":0,"dur":1},{"name":"gen_bytecode_push_name","cat":"function","ph":"X","ts":884,"pid":9036,"tid":0,"dur":1},{"name":"gen_ptr","cat":"function","ph":"X","ts":884,"pid":9036,"tid":0,"dur":1},{"name":"gen_bytecode_initvar","cat":"function","ph":"X","ts":885,"pid":9036,"tid":0,"dur":1},{"name":"gen_bytecode_push_const","cat":"function","ph":"X","ts":886,"pid":9036,"tid":0,"dur":1},{"name":"gen_const","cat":"function","ph":"X","ts":886,"pid":9036,"tid":0,"dur":1},{"name":"gen_bytecode_push_const","cat":"function","ph":"X","ts":887,"pid":9036,"tid":0,"dur":1},{"name":"gen_const","cat":"function","ph":"X","ts":887,"pid":9036,"tid":0,"dur":1},{"name":"gen_bytecode_push_const","cat":"function","ph":"X","ts":888,"pid":9036,"tid":0,"dur":1},{"name":"gen_const","cat":"function","ph":"X","ts":889,"pid":9036,"tid":0,"dur":1},{"name":"gen_bytecode_mod","cat":"function","ph":"X","ts":889,"pid":9036,"tid":0,"dur":1},{"name":"gen_bytecode_push_const","cat":"function","ph":"X","ts":890,"pid":9036,"tid":0,"dur":1},{"name":"gen_const","cat":"function","ph":"X","ts":890,"pid":9036,"tid":0,"dur":1},{"name":"gen_bytecode_div","cat":"function","ph":"X","ts":891,"pid":9036,"tid":0,"dur":1},{"name":"gen_bytecode_add","cat":"function","ph":"X","ts":891,"pid":9036,"tid":0,"dur":1},{"name":"gen_bytecode_push_name","cat":"function","ph":"X","ts":892,"pid":9036,"tid":0,"dur":1},{"name":"gen_ptr","cat":"function","ph":"X","ts":893,"pid":9036,"tid":0,"dur":1},{"name":"gen_bytecode_initvar","cat":"function","ph":"X","ts":893,"pid":9036,"tid":0,"dur":1},{"name":"gen_bytecode_push_const","cat":"function","ph":"X","ts":894,"pid":9036,"tid":0,"dur":1},{"name":"gen_const","cat":"function","ph":"X","ts":894,"pid":9036,"tid":0,"dur":1},{"name":"gen_bytecode_push_const","cat":"function","ph":"X","ts":895,"pid":9036,"tid":0,"dur":1},{"name":"gen_const","cat":"function","ph":"X","ts":896,"pid":9036,"tid":0,"dur":1},{"name":"gen_bytecode_sub","cat":"function","ph":"X","ts":896,"pid":9036,"tid":0,"dur":1},{"name":"gen_bytecode_push_const","cat":"function","ph":"X","ts":897,"pid":9036,"tid":0,"dur":1},{"name":"gen_const","cat":"function","ph":"X","ts":897,"pid":9036,"tid":0,"dur":1},{"name":"gen_bytecode_sub","cat":"function","ph":"X","ts":898,"pid":9036,"tid":0,"dur":1},{"name":"gen_bytecode_push_const","cat":"function","ph":"X","ts":899,"pid":9036,"tid":0,"dur":1},{"name":"gen_const","cat":"function","ph":"X","ts":899,"pid":9036,"tid":0,"dur":1},{"name":"gen_bytecode_negate","cat":"function","ph":"X","ts":900,"pid":9036,"tid":0,"dur":1},{"name":"gen_bytecode_push_const","cat":"function","ph":"X","ts":901,"pid":9036,"tid":0,"dur":1},{"name":"gen_const","cat":"function","ph":"X","ts":901,"pid":9036,"tid":0,"dur":1},{"name":"gen_bytecode_mul","cat":"function","ph":"X","ts":902,"pid":9036,"tid":0,"dur":1},{"name":"gen_bytecode_sub","cat":"function","ph":"X","ts":902,"pid":9036,"tid":0,"dur":1},{"name":"gen_bytecode_push_const","cat":"function","ph":"X","ts":903,"pid":9036,"tid":0,"dur":1},{"name":"gen_const","cat":"function","ph":"X","ts":903,"pid":9036,"tid":0,"dur":1},{"name":"gen_bytecode_add","cat":"function","ph":"X","ts":904,"pid":9036,"tid":0,"dur":1},{"name":"gen_bytecode_push_name","cat":"function","ph":"X","ts":905,"pid":9036,"tid":0,"dur":1},{"name":"gen_ptr","cat":"function","ph":"X","ts":905,"pid":9036,"tid":0,"dur":1},{"name":"gen_bytecode_initvar","cat":"function","ph":"X","ts":906,"pid":9036,"tid":0,"dur":1},{"name":"gen_bytecode_ref_iden","cat":"function","ph":"X","ts":906,"pid":9036,"tid":0,"dur":1},{"name":"gen_ptr","cat":"function","ph":"X","ts":907,"pid":9036,"tid":0,"dur":1},{"name":"gen_bytecode_ref_iden","cat":"function","ph":"X","ts":908,"pid":9036,"tid":0,"dur":1},{"name":"gen_ptr","cat":"function","ph":"X","ts":908,"pid":9036,"tid":0,"dur":1},{"name":"gen_bytecode_add","cat":"function","ph":"X","ts":909,"pid":9036,"tid":0,"dur":1},{"name":"gen_bytecode_ref_iden","cat":"function","ph":"X","ts":909,"pid":9036,"tid":0,"dur":1},{"name":"gen_ptr","cat":"function","ph":"X","ts":910,"pid":9036,"tid":0,"dur":1},{"name":"gen_bytecode_add","cat":"function","ph":"X","ts":910,"pid":9036,"tid":0,"dur":1},{"name":"gen_bytecode_push_name","cat":"function","ph":"X","ts":911,"pid":9036,"tid":0,"dur":1},{"name":"gen_ptr","cat":"function","ph":"X","ts":912,"pid":9036,"tid":0,"dur":1},{"name":"gen_bytecode_initvar","cat":"function","ph":"X","ts":912,"pid":9036,"tid":0,"dur":1},{"name":"gen_bytecode_push_const","cat":"function","ph":"X","ts":913,"pid":9036,"tid":0,"dur":1},{"name":"gen_const","cat":"function","ph":"X","ts":913,"pid":9036,"tid":0,"dur":1},{"name":"gen_bytecode_push_const","cat":"function","ph":"X","ts":914,"pid":9036,"tid":0,"dur":1},{"name":"gen_const","cat":"function","ph":"X","ts":914,"pid":9036,"tid":0,"dur":1},{"name":"gen_bytecode_push_const","cat":"function","ph":"X","ts":915,"pid":9036,"tid":0,"dur":1},{"name":"gen_const","cat":"function","ph":"X","ts":916,"pid":9036,"tid":0,"dur":1},{"name":"gen_bytecode_push_const","cat":"function","ph":"X","ts":916,"pid":9036,"tid":0,"dur":1},{"name":"gen_const","cat":"function","ph":"X","ts":917,"pid":9036,"tid":0,"dur":1},{"name":"gen_bytecode_push_const","cat":"function","ph":"X","ts":917,"pid":9036,"tid":0,"dur":1},{"name":"gen_const","cat":"function","ph":"X","ts":918,"pid":9036,"tid":0,"dur":1},{"name":"gen_bytecode_mul","cat":"function","ph":"X","ts":919,"pid":9036,"tid":0,"dur":1},{"name":"gen_bytecode_div","cat":"function","ph":"X","ts":919,"pid":9036,"tid":0,"dur":1},{"name":"gen_bytecode_mul","cat":"function","ph":"X","ts":920,"pid":9036,"tid":0,"dur":1},{"name":"gen_bytecode_add","cat":"function","ph":"X","ts":920,"pid":9036,"tid":0,"dur":1},{"name":"gen_bytecode_push_const","cat":"function","ph":"X","ts":921,"pid":9036,"tid":0,"dur":1},{"name":"gen_const","cat":"function","ph":"X","ts":921,"pid":9036,"tid":0,"dur":1},{"name":"gen_bytecode_add","cat":"function","ph":"X","ts":922,"pid":9036,"tid":0,"dur":1},{"name":"gen_bytecode_push_const","cat":"function","ph":"X","ts":922,"pid":9036,"tid":0,"dur":1},{"name":"gen_const","cat":"function","ph":"X","ts":923,"pid":9036,"tid":0,"dur":1},{"name":"gen_bytecode_sub","cat":"function","ph":"X","ts":924,"pid":9036,"tid":0,"dur":1},{"name":"gen_bytecode_push_const","cat":"function","ph":"X","ts":924,"pid":9036,"tid":0,"dur":1},{"name":"gen_const","cat":"function","ph":"X","ts":925,"pid":9036,"tid":0,"dur":1},{"name":"gen_bytecode_sub","cat":"function","ph":"X","ts":925,"pid":9036,"tid":0,"dur":1},{"name":"gen_bytecode_push_const","cat":"function","ph":"X","ts":926,"pid":9036,"tid":0,"dur":1},{"name":"gen_const","cat":"function","ph":"X","ts":927,"pid":9036,"tid":0,"dur":1},{"name":"gen_bytecode_mul","cat":"function","ph":"X","ts":927,"pid":9036,"tid":0,"dur":1},{"name":"gen_bytecode_push_const","cat":"function","ph":"X","ts":928,"pid":9036,"tid":0,"dur":1},{"name":"gen_const","cat":"function","ph":"X","ts":928,"pid":9036,"tid":0,"dur":1},{"name":"gen_bytecode_push_const","cat":"function","ph":"X","ts":929,"pid":9036,"tid":0,"dur":1},{"name":"gen_const","cat":"function","ph":"X","ts":929,"pid":9036,"tid":0,"dur":1},{"name":"gen_bytecode_add","cat":"function","ph":"X","ts":930,"pid":9036,"tid":0,"dur":1},{"name":"gen_bytecode_add","cat":"function","ph":"X","ts":931,"pid":9036,"tid":0,"dur":1},{"name":"gen_bytecode_push_const","cat":"function","ph":"X","ts":931,"pid":9036,"tid":0,"dur":1},{"name":"gen_const","cat":"function","ph":"X","ts":932,"pid":9036,"tid":0,"dur":1},{"name":"gen_bytecode_push_const","cat":"function","ph":"X","ts":932,"pid":9036,"tid":0,"dur":1},{"name":"gen_const","cat":"function","ph":"X","ts":933,"pid":9036,"tid":0,"dur":1},{"name":"gen_bytecode_sub","cat":"function","ph":"X","ts":933,"pid":9036,"tid":0,"dur":1},{"name":"gen_bytecode_push_const","cat":"function","ph":"X","ts":934,"pid":9036,"tid":0,"dur":1},{"name":"gen_const","cat":"function","ph":"X","ts":934,"pid":9036,"tid":0,"dur":1},{"name":"gen_bytecode_sub","cat":"function","ph":"X","ts":935,"pid":9036,"tid":0,"dur":1},{"name":"gen_bytecode_add","cat":"function","ph":"X","ts":936,"pid":9036,"tid":0,"dur":1},{"name":"gen_bytecode_push_name","cat":"function","ph":"X","ts":936,"pid":9036,"tid":0,"dur":1},{"name":"gen_ptr","cat":"function","ph":"X","ts":937,"pid":9036,"tid":0,"dur":1},{"name":"gen_bytecode_initvar","cat":"function","ph":"X","ts":937,"pid":9036,"tid":0,"dur":1},{"name":"gen_bytecode_push_const","cat":"function","ph":"X","ts":938,"pid":9036,"tid":0,"dur":1},{"name":"gen_const","cat":"function","ph":"X","ts":938,"pid":9036,"tid":0,"dur":1},{"name":"gen_bytecode_ref_iden","cat":"function","ph":"X","ts":939,"pid":9036,"tid":0,"dur":1},{"name":"gen_ptr","cat":"function","ph":"X","ts":940,"pid":9036,"tid":0,"dur":1},{"name":"gen_bytecode_assign","cat":"function","ph":"X","ts":940,"pid":9036,"tid":0,"dur":1},{"name":"gen_bytecode_ref_iden","cat":"function","ph":"X","ts":941,"pid":9036,"tid":0,"dur":1},{"name":"gen_ptr","cat":"function","ph":"X","ts":941,"pid":9036,"tid":0,"dur":1},{"name":"gen_bytecode_ref_iden","cat":"function","ph":"X","ts":942,"pid":9036,"tid":0,"dur":1},{"name":"gen_ptr","cat":"function","ph":"X","ts":943,"pid":9036,"tid":0,"dur":1},{"name":"gen_bytecode_add_assign","cat":"function","ph":"X","ts":943,"pid":9036,"tid":0,"dur":1},{"name":"gen_bytecode_ref_iden","cat":"function","ph":"X","ts":944,"pid":9036,"tid":0,"dur":1},{"name":"gen_ptr","cat":"function","ph":"X","ts":944,"pid":9036,"tid":0,"dur":1},{"name":"gen_bytecode_ref_iden","cat":"function","ph":"X","ts":945,"pid":9036,"tid":0,"dur":1},{"name":"gen_ptr","cat":"function","ph":"X","ts":945,"pid":9036,"tid":0,"dur":1},{"name":"fetching trace data","cat":"function","ph":"X","ts":946,"pid":9036,"tid":0,"dur":219},{"name":"gen_bytecode_sub_assign","cat":"function","ph":"X","ts":946,"pid":9036,"tid":0,"dur":1},{"name":"gen_bytecode_ref_iden","cat":"function","ph":"X","ts":1167,"pid":9036,"tid":0,"dur":1},{"name":"gen_ptr","cat":"function","ph":"X","ts":1168,"pid":9036,"tid":0,"dur":1},{"name":"gen_bytecode_ref_iden","cat":"function","ph":"X","ts":1169,"pid":9036,"tid":0,"dur":1},{"name":"gen_ptr","cat":"function","ph":"X","ts":1169,"pid":9036,"tid":0,"dur":1},{"name":"gen_bytecode_mul_assign","cat":"function","ph":"X","ts":1170,"pid":9036,"tid":0,"dur":1},{"name":"gen_bytecode_ref_iden","cat":"function","ph":"X","ts":1170,"pid":9036,"tid":0,"dur":1},{"name":"gen_ptr","cat":"function","ph":"X","ts":1171,"pid":9036,"tid":0,"dur":1},{"name":"gen_bytecode_ref_iden","cat":"function","ph":"X","ts":1172,"pid":9036,"tid":0,"dur":1},{"name":"gen_ptr","cat":"function","ph":"X","ts":1172,"pid":9036,"tid":0,"dur":1},{"name":"gen_bytecode_div_assign","cat":"function","ph":"X","ts":1173,"pid":9036,"tid":0,"dur":1},{"name":"gen_bytecode_ref_iden","cat":"function","ph":"X","ts":1173,"pid":9036,"tid":0,"dur":1},{"name":"gen_ptr","cat":"function","ph":"X","ts":1174,"pid":9036,"tid":0,"dur":1},{"name":"gen_bytecode_ref_iden","cat":"function","ph":"X","ts":1175,"pid":9036,"tid":0,"dur":1},{"name":"gen_ptr","cat":"function","ph":"X","ts":1175,"pid":9036,"tid":0,"dur":1},{"name":"gen_bytecode_assign","cat":"function","ph":"X","ts":1176,"pid":9036,"tid":0,"dur":1},{"name":"gen_bytecode_ref_iden","cat":"function","ph":"X","ts":1176,"pid":9036,"tid":0,"dur":1},{"name":"gen_ptr","cat":"function","ph":"X","ts":1177,"pid":9036,"tid":0,"dur":1},{"name":"gen_bytecode_access_iden","cat":"function","ph":"X","ts":1177,"pid":9036,"tid":0,"dur":1},{"name":"gen_ptr","cat":"function","ph":"X","ts":1178,"pid":9036,"tid":0,"dur":1},{"name":"gen_bytecode_pop","cat":"function","ph":"X","ts":1179,"pid":9036,"tid":0,"dur":1},{"name":"gen_bytecode_ref_iden","cat":"function","ph":"X","ts":1179,"pid":9036,"tid":0,"dur":1},{"name":"gen_ptr","cat":"function","ph":"X","ts":1180,"pid":9036,"tid":0,"dur":1},{"name":"gen_bytecode_access_iden","cat":"function","ph":"X","ts":1180,"pid":9036,"tid":0,"dur":1},{"name":"gen_ptr","cat":"function","ph":"X","ts":1181,"pid":9036,"tid":0,"dur":1},{"name":"gen_bytecode_access_iden","cat":"function","ph":"X","ts":1181,"pid":9036,"tid":0,"dur":1},{"name":"gen_ptr","cat":"function","ph":"X","ts":1182,"pid":9036,"tid":0,"dur":1},{"name":"gen_bytecode_pop","cat":"function","ph":"X","ts":1182,"pid":9036,"tid":0,"dur":1},{"name":"gen_bytecode_ref_iden","cat":"function","ph":"X","ts":1183,"pid":9036,"tid":0,"dur":1},{"name":"gen_ptr","cat":"function","ph":"X","ts":1184,"pid":9036,"tid":0,"dur":1},{"name":"gen_bytecode_access_iden","cat":"function","ph":"X","ts":1184,"pid":9036,"tid":0,"dur":1},{"name":"gen_ptr","cat":"function","ph":"X","ts":1185,"pid":9036,"tid":0,"dur":1},{"name":"gen_bytecode_access_iden","cat":"function","ph":"X","ts":1185,"pid":9036,"tid":0,"dur":1},{"name":"gen_ptr","cat":"function","ph":"X","ts":1186,"pid":9036,"tid":0,"dur":1},{"name":"gen_bytecode_access_iden","cat":"function","ph":"X","ts":1186,"pid":9036,"tid":0,"dur":1},{"name":"gen_ptr","cat":"function","ph":"X","ts":1187,"pid":9036,"tid":0,"dur":1},{"name":"gen_bytecode_pop","cat":"function","ph":"X","ts":1187,"pid":9036,"tid":0,"dur":1},{"name":"gen_bytecode_ref_iden","cat":"function","ph":"X","ts":1188,"pid":9036,"tid":0,"dur":1},{"name":"gen_ptr","cat":"function","ph":"X","ts":1188,"pid":9036,"tid":0,"dur":1},{"name":"gen_bytecode_access_iden","cat":"function","ph":"X","ts":1189,"pid":9036,"tid":0,"dur":1},{"name":"gen_ptr","cat":"function","ph":"X","ts":1189,"pid":9036,"tid":0,"dur":1},{"name":"gen_bytecode_access_iden","cat":"function","ph":"X","ts":1190,"pid":9036,"tid":0,"dur":1},{"name":"gen_ptr","cat":"function","ph":"X","ts":1190,"pid":9036,"tid":0,"dur":1},{"name":"gen_bytecode_access_iden","cat":"function","ph":"X","ts":1191,"pid":9036,"tid":0,"dur":1},{"name":"gen_ptr","cat":"function","ph":"X","ts":1191,"pid":9036,"tid":0,"dur":1},{"name":"gen_bytecode_access_iden","cat":"function","ph":"X","ts":1192,"pid":9036,"tid":0,"dur":1},{"name":"gen_ptr","cat":"function","ph":"X","ts":1193,"pid":9036,"tid":0,"dur":1},{"name":"gen_bytecode_pop","cat":"function","ph":"X","ts":1193,"pid":9036,"tid":0,"dur":1},{"name":"gen_bytecode_push_name","cat":"function","ph":"X","ts":1194,"pid":9036,"tid":0,"dur":1},{"name":"gen_ptr","cat":"function","ph":"X","ts":1194,"pid":9036,"tid":0,"dur":1},{"name":"gen_bytecode_push_name","cat":"function","ph":"X","ts":1195,"pid":9036,"tid":0,"dur":1},{"name":"gen_ptr","cat":"function","ph":"X","ts":1195,"pid":9036,"tid":0,"dur":1},{"name":"gen_bytecode_funcdef","cat":"function","ph":"X","ts":1196,"pid":9036,"tid":0,"dur":1},{"name":"gen_const","cat":"function","ph":"X","ts":1197,"pid":9036,"tid":0,"dur":1},{"name":"gen_bytecode_ref_iden","cat":"function","ph":"X","ts":1197,"pid":9036,"tid":0,"dur":1},{"name":"gen_ptr","cat":"function","ph":"X","ts":1198,"pid":9036,"tid":0,"dur":1},{"name":"gen_bytecode_ref_iden","cat":"function","ph":"X","ts":1199,"pid":9036,"tid":0,"dur":1},{"name":"gen_ptr","cat":"function","ph":"X","ts":1199,"pid":9036,"tid":0,"dur":1},{"name":"gen_bytecode_mul","cat":"function","ph":"X","ts":1200,"pid":9036,"tid":0,"dur":1},{"name":"gen_bytecode_push_name","cat":"function","ph":"X","ts":1201,"pid":9036,"tid":0,"dur":1},{"name":"gen_ptr","cat":"function","ph":"X","ts":1201,"pid":9036,"tid":0,"dur":1},{"name":"gen_bytecode_initvar","cat":"function","ph":"X","ts":1202,"pid":9036,"tid":0,"dur":1},{"name":"gen_bytecode_ref_iden","cat":"function","ph":"X","ts":1202,"pid":9036,"tid":0,"dur":1},{"name":"gen_ptr","cat":"function","ph":"X","ts":1203,"pid":9036,"tid":0,"dur":1},{"name":"gen_bytecode_funcend","cat":"function","ph":"X","ts":1204,"pid":9036,"tid":0,"dur":1},{"name":"gen_bytecode_ref_iden","cat":"function","ph":"X","ts":1204,"pid":9036,"tid":0,"dur":1},{"name":"gen_ptr","cat":"function","ph":"X","ts":1205,"pid":9036,"tid":0,"dur":1},{"name":"gen_bytecode_ref_iden","cat":"function","ph":"X","ts":1205,"pid":9036,"tid":0,"dur":1},{"name":"gen_ptr","cat":"function","ph":"X","ts":1206,"pid":9036,"tid":0,"dur":1},{"name":"gen_bytecode_push_const","cat":"function","ph":"X","ts":1207,"pid":9036,"tid":0,"dur":1},{"name":"gen_const","cat":"function","ph":"X","ts":1207,"pid":9036,"tid":0,"dur":1},{"name":"gen_bytecode_funcall","cat":"function","ph":"X","ts":1208,"pid":9036,"tid":0,"dur":1},{"name":"gen_const","cat":"function","ph":"X","ts":1209,"pid":9036,"tid":0,"dur":1},{"name":"gen_bytecode_funcall","cat":"function","ph":"X","ts":1209,"pid":9036,"tid":0,"dur":1},{"name":"gen_const","cat":"function","ph":"X","ts":1210,"pid":9036,"tid":0,"dur":1},{"name":"gen_bytecode_push_name","cat":"function","ph":"X","ts":1210,"pid":9036,"tid":0,"dur":1},{"name":"gen_ptr","cat":"function","ph":"X","ts":1211,"pid":9036,"tid":0,"dur":1},{"name":"gen_bytecode_initvar","cat":"function","ph":"X","ts":1212,"pid":9036,"tid":0,"dur":1},{"name":"gen_bytecode_push_const","cat":"function","ph":"X","ts":1212,"pid":9036,"tid":0,"dur":1},{"name":"gen_const","cat":"function","ph":"X","ts":1213,"pid":9036,"tid":0,"dur":1},{"name":"gen_bytecode_ref_iden","cat":"function","ph":"X","ts":1213,"pid":9036,"tid":0,"dur":1},{"name":"gen_ptr","cat":"function","ph":"X","ts":1214,"pid":9036,"tid":0,"dur":1},{"name":"gen_bytecode_add_assign","cat":"function","ph":"X","ts":1214,"pid":9036,"tid":0,"dur":1},{"name":"gen_bytecode_push_name","cat":"function","ph":"X","ts":1215,"pid":9036,"tid":0,"dur":1},{"name":"gen_ptr","cat":"function","ph":"X","ts":1216,"pid":9036,"tid":0,"dur":1},{"name":"gen_bytecode_push_name","cat":"function","ph":"X","ts":1216,"pid":9036,"tid":0,"dur":1},{"name":"gen_ptr","cat":"function","ph":"X","ts":1217,"pid":9036,"tid":0,"dur":1},{"name":"gen_bytecode_push_name","cat":"function","ph":"X","ts":1217,"pid":9036,"tid":0,"dur":1},{"name":"gen_ptr","cat":"function","ph":"X","ts":1218,"pid":9036,"tid":0,"dur":1},{"name":"gen_bytecode_funcdef","cat":"function","ph":"X","ts":1218,"pid":9036,"tid":0,"dur":1},{"name":"gen_const","cat":"function","ph":"X","ts":1219,"pid":9036,"tid":0,"dur":1},{"name":"gen_bytecode_ref_iden","cat":"function","ph":"X","ts":1220,"pid":9036,"tid":0,"dur":1},{"name":"gen_ptr","cat":"function","ph":"X","ts":1220,"pid":9036,"tid":0,"dur":1},{"name":"gen_bytecode_ref_iden","cat":"function","ph":"X","ts":1221,"pid":9036,"tid":0,"dur":1},{"name":"gen_ptr","cat":"function","ph":"X","ts":1221,"pid":9036,"tid":0,"dur":1},{"name":"gen_bytecode_add","cat":"function","ph":"X","ts":1222,"pid":9036,"tid":0,"dur":1},{"name":"gen_bytecode_push_name","cat":"function","ph":"X","ts":1222,"pid":9036,"tid":0,"dur":1},{"name":"gen_ptr","cat":"function","ph":"X","ts":1223,"pid":9036,"tid":0,"dur":1},{"name":"gen_bytecode_initvar","cat":"function","ph":"X","ts":1223,"pid":9036,"tid":0,"dur":1},{"name":"gen_bytecode_ref_iden","cat":"function","ph":"X","ts":1224,"pid":9036,"tid":0,"dur":1},{"name":"gen_ptr","cat":"function","ph":"X","ts":1224,"pid":9036,"tid":0,"dur":1},{"name":"gen_bytecode_funcend","cat":"function","ph":"X","ts":1225,"pid":9036,"tid":0,"dur":1},{"name":"gen_bytecode_ref_iden","cat":"function","ph":"X","ts":1225,"pid":9036,"tid":0,"dur":1},{"name":"gen_ptr","cat":"function","ph":"X","ts":1226,"pid":9036,"tid":0,"dur":1},{"name":"gen_bytecode_ref_iden","cat":"function","ph":"X","ts":1227,"pid":9036,"tid":0,"dur":1},{"name":"gen_ptr","cat":"function","ph":"X","ts":1227,"pid":9036,"tid":0,"dur":1},{"name":"gen_bytecode_push_const","cat":"function","ph":"X","ts":1228,"pid":9036,"tid":0,"dur":1},{"name":"gen_const","cat":"function","ph":"X","ts":1228,"pid":9036,"tid":0,"dur":1},{"name":"gen_bytecode_push_const","cat":"function","ph":"X","ts":1229,"pid":9036,"tid":0,"dur":1},{"name":"gen_const","cat":"function","ph":"X","ts":1229,"pid":9036,"tid":0,"dur":1},{"name":"gen_bytecode_funcall","cat":"function","ph":"X","ts":1230,"pid":9036,"tid":0,"dur":1},{"name":"gen_const","cat":"function","ph":"X","ts":1230,"pid":9036,"tid":0,"dur":1},{"name":"gen_bytecode_ref_iden","cat":"function","ph":"X","ts":1231,"pid":9036,"tid":0,"dur":1},{"name":"gen_ptr","cat":"function","ph":"X","ts":1232,"pid":9036,"tid":0,"dur":1},{"name":"gen_bytecode_push_const","cat":"function","ph":"X","ts":1232,"pid":9036,"tid":0,"dur":1},{"name":"gen_const","cat":"function","ph":"X","ts":1233,"pid":9036,"tid":0,"dur":1},{"name":"gen_bytecode_push_const","cat":"function","ph":"X","ts":1233,"pid":9036,"tid":0,"dur":1},{"name":"gen_const","cat":"function","ph":"X","ts":1234,"pid":9036,"tid":0,"dur":1},{"name":"gen_bytecode_funcall","cat":"function","ph":"X","ts":1235,"pid":9036,"tid":0,"dur":1},{"name":"gen_const","cat":"function","ph":"X","ts":1235,"pid":9036,"tid":0,"dur":1},{"name":"gen_bytecode_funcall","cat":"function","ph":"X","ts":1236,"pid":9036,"tid":0,"dur":1},{"name":"gen_const","cat":"function","ph":"X","ts":1236,"pid":9036,"tid":0,"dur":1},{"name":"gen_bytecode_push_name","cat":"function","ph":"X","ts":1237,"pid":9036,"tid":0,"dur":1},{"name":"gen_ptr","cat":"function","ph":"X","ts":1238,"pid":9036,"tid":0,"dur":1},{"name":"gen_bytecode_initvar","cat":"function","ph":"X","ts":1238,"pid":9036,"tid":0,"dur":1},{"name":"gen_bytecode_push_const","cat":"function","ph":"X","ts":1239,"pid":9036,"tid":0,"dur":1},{"name":"gen_const","cat":"function","ph":"X","ts":1239,"pid":9036,"tid":0,"dur":1},{"name":"gen_bytecode_ref_iden","cat":"function","ph":"X","ts":1240,"pid":9036,"tid":0,"dur":1},{"name":"gen_ptr","cat":"function","ph":"X","ts":1240,"pid":9036,"tid":0,"dur":1},{"name":"gen_bytecode_add_assign","cat":"function","ph":"X","ts":1241,"pid":9036,"tid":0,"dur":1},{"name":"vm_gen_bytecode","cat":"function","ph":"X","ts":854,"pid":9036,"tid":0,"dur":387},{"name":"debug log","cat":"function","ph":"X","ts":1242,"pid":9036,"tid":0,"dur":1},{"name":"vm run","cat":"function","ph":"X","ts":1244,"pid":9036,"tid":0,"dur":39},{"name":"free_ast","cat":"function","ph":"X","ts":1286,"pid":9036,"tid":0,"dur":6},{"name":"free_parser","cat":"function","ph":"X","ts":1293,"pid":9036,"tid":0,"dur":1},{"name":"free_environment","cat":"function","ph":"X","ts":1294,"pid":9036,"tid":0,"dur":14},{"name":"free_vm","cat":"function","ph":"X","ts":1294,"pid":9036,"tid":0,"dur":15}]}